Compiled from "SecuredObjectDAO.java"
public class org.egovframe.rte.fdl.security.secureobject.impl.SecuredObjectDAO {
  public static final org.slf4j.Logger LOGGER;

  public static final java.lang.String DEF_ROLES_AND_URL_QUERY;

  public static final java.lang.String DEF_REGEX_MATCHED_REQUEST_MAPPING_QUERY_ORACLE10G;

  public static final java.lang.String DEF_HIERARCHICAL_ROLES_QUERY;

  private final org.egovframe.rte.fdl.security.config.EgovSecurityConfig config;

  private java.lang.String sqlRolesAndUrl;

  private java.lang.String sqlRegexMatchedRequestMapping;

  private java.lang.String sqlHierarchicalRoles;

  private org.springframework.jdbc.core.namedparam.NamedParameterJdbcTemplate namedParameterJdbcTemplate;

  public org.egovframe.rte.fdl.security.secureobject.impl.SecuredObjectDAO(org.egovframe.rte.fdl.security.config.EgovSecurityConfig);
    Code:
       0: aload_0
       1: invokespecial #1                  // Method java/lang/Object."<init>":()V
       4: aload_0
       5: aload_1
       6: putfield      #7                  // Field config:Lorg/egovframe/rte/fdl/security/config/EgovSecurityConfig;
       9: aload_0
      10: ldc           #13                 // String SELECT a.resource_pattern url, b.authority authority FROM SECURED_RESOURCES a, SECURED_RESOURCES_ROLE b WHERE a.resource_id = b.resource_id AND a.resource_type = \'url\' ORDER BY a.sort_order
      12: putfield      #15                 // Field sqlRolesAndUrl:Ljava/lang/String;
      15: aload_0
      16: ldc           #19                 // String SELECT a.resource_pattern uri, b.authority authority FROM secured_resources a, secured_resources_role b WHERE a.resource_id = b.resource_id AND a.resource_id =   ( SELECT resource_id FROM     ( SELECT resource_id, ROW_NUMBER() OVER (ORDER BY sort_order) resource_order FROM secured_resources c       WHERE REGEXP_LIKE ( :url, c.resource_pattern )       AND c.resource_type = \'url\'       ORDER BY c.sort_order )    WHERE resource_order = 1 )
      18: putfield      #21                 // Field sqlRegexMatchedRequestMapping:Ljava/lang/String;
      21: aload_0
      22: ldc           #24                 // String SELECT a.child_role child, a.parent_role parent FROM ROLES_HIERARCHY a LEFT JOIN ROLES_HIERARCHY b on (a.child_role = b.parent_role)
      24: putfield      #26                 // Field sqlHierarchicalRoles:Ljava/lang/String;
      27: return
    LineNumberTable:
      line 93: 0
      line 94: 4
      line 95: 9
      line 96: 15
      line 97: 21
      line 98: 27
    LocalVariableTable:
      Start  Length  Slot  Name   Signature
          0      28     0  this   Lorg/egovframe/rte/fdl/security/secureobject/impl/SecuredObjectDAO;
          0      28     1 config   Lorg/egovframe/rte/fdl/security/config/EgovSecurityConfig;

  public java.lang.String getSqlRolesAndUrl();
    Code:
       0: aload_0
       1: getfield      #15                 // Field sqlRolesAndUrl:Ljava/lang/String;
       4: areturn
    LineNumberTable:
      line 101: 0
    LocalVariableTable:
      Start  Length  Slot  Name   Signature
          0       5     0  this   Lorg/egovframe/rte/fdl/security/secureobject/impl/SecuredObjectDAO;

  public void setSqlRolesAndUrl(java.lang.String);
    Code:
       0: aload_0
       1: aload_1
       2: putfield      #15                 // Field sqlRolesAndUrl:Ljava/lang/String;
       5: return
    LineNumberTable:
      line 105: 0
      line 106: 5
    LocalVariableTable:
      Start  Length  Slot  Name   Signature
          0       6     0  this   Lorg/egovframe/rte/fdl/security/secureobject/impl/SecuredObjectDAO;
          0       6     1 sqlRolesAndUrl   Ljava/lang/String;

  public java.lang.String getSqlRegexMatchedRequestMapping();
    Code:
       0: aload_0
       1: getfield      #21                 // Field sqlRegexMatchedRequestMapping:Ljava/lang/String;
       4: areturn
    LineNumberTable:
      line 109: 0
    LocalVariableTable:
      Start  Length  Slot  Name   Signature
          0       5     0  this   Lorg/egovframe/rte/fdl/security/secureobject/impl/SecuredObjectDAO;

  public void setSqlRegexMatchedRequestMapping(java.lang.String);
    Code:
       0: aload_0
       1: aload_1
       2: putfield      #21                 // Field sqlRegexMatchedRequestMapping:Ljava/lang/String;
       5: return
    LineNumberTable:
      line 113: 0
      line 114: 5
    LocalVariableTable:
      Start  Length  Slot  Name   Signature
          0       6     0  this   Lorg/egovframe/rte/fdl/security/secureobject/impl/SecuredObjectDAO;
          0       6     1 sqlRegexMatchedRequestMapping   Ljava/lang/String;

  public java.lang.String getSqlHierarchicalRoles();
    Code:
       0: aload_0
       1: getfield      #26                 // Field sqlHierarchicalRoles:Ljava/lang/String;
       4: areturn
    LineNumberTable:
      line 117: 0
    LocalVariableTable:
      Start  Length  Slot  Name   Signature
          0       5     0  this   Lorg/egovframe/rte/fdl/security/secureobject/impl/SecuredObjectDAO;

  public void setSqlHierarchicalRoles(java.lang.String);
    Code:
       0: aload_0
       1: aload_1
       2: putfield      #26                 // Field sqlHierarchicalRoles:Ljava/lang/String;
       5: return
    LineNumberTable:
      line 121: 0
      line 122: 5
    LocalVariableTable:
      Start  Length  Slot  Name   Signature
          0       6     0  this   Lorg/egovframe/rte/fdl/security/secureobject/impl/SecuredObjectDAO;
          0       6     1 sqlHierarchicalRoles   Ljava/lang/String;

  public void setDataSource(javax.sql.DataSource);
    Code:
       0: aload_0
       1: new           #29                 // class org/springframework/jdbc/core/namedparam/NamedParameterJdbcTemplate
       4: dup
       5: aload_1
       6: invokespecial #31                 // Method org/springframework/jdbc/core/namedparam/NamedParameterJdbcTemplate."<init>":(Ljavax/sql/DataSource;)V
       9: putfield      #34                 // Field namedParameterJdbcTemplate:Lorg/springframework/jdbc/core/namedparam/NamedParameterJdbcTemplate;
      12: return
    LineNumberTable:
      line 125: 0
      line 126: 12
    LocalVariableTable:
      Start  Length  Slot  Name   Signature
          0      13     0  this   Lorg/egovframe/rte/fdl/security/secureobject/impl/SecuredObjectDAO;
          0      13     1 dataSource   Ljavax/sql/DataSource;

  public void securedObjectConfigInit();
    Code:
       0: aload_0
       1: getfield      #7                  // Field config:Lorg/egovframe/rte/fdl/security/config/EgovSecurityConfig;
       4: ifnonnull     17
       7: new           #38                 // class org/springframework/beans/factory/NoSuchBeanDefinitionException
      10: dup
      11: ldc           #40                 // String ### SecuredObjectDAO EgovSecurityProperties not defined
      13: invokespecial #42                 // Method org/springframework/beans/factory/NoSuchBeanDefinitionException."<init>":(Ljava/lang/String;)V
      16: athrow
      17: aload_0
      18: getfield      #7                  // Field config:Lorg/egovframe/rte/fdl/security/config/EgovSecurityConfig;
      21: invokevirtual #45                 // Method org/egovframe/rte/fdl/security/config/EgovSecurityConfig.getSqlRolesAndUrl:()Ljava/lang/String;
      24: invokestatic  #51                 // Method org/springframework/util/StringUtils.hasText:(Ljava/lang/String;)Z
      27: ifeq          41
      30: aload_0
      31: aload_0
      32: getfield      #7                  // Field config:Lorg/egovframe/rte/fdl/security/config/EgovSecurityConfig;
      35: invokevirtual #45                 // Method org/egovframe/rte/fdl/security/config/EgovSecurityConfig.getSqlRolesAndUrl:()Ljava/lang/String;
      38: putfield      #15                 // Field sqlRolesAndUrl:Ljava/lang/String;
      41: aload_0
      42: getfield      #7                  // Field config:Lorg/egovframe/rte/fdl/security/config/EgovSecurityConfig;
      45: invokevirtual #57                 // Method org/egovframe/rte/fdl/security/config/EgovSecurityConfig.getSqlRegexMatchedRequestMapping:()Ljava/lang/String;
      48: invokestatic  #51                 // Method org/springframework/util/StringUtils.hasText:(Ljava/lang/String;)Z
      51: ifeq          65
      54: aload_0
      55: aload_0
      56: getfield      #7                  // Field config:Lorg/egovframe/rte/fdl/security/config/EgovSecurityConfig;
      59: invokevirtual #57                 // Method org/egovframe/rte/fdl/security/config/EgovSecurityConfig.getSqlRegexMatchedRequestMapping:()Ljava/lang/String;
      62: putfield      #21                 // Field sqlRegexMatchedRequestMapping:Ljava/lang/String;
      65: aload_0
      66: getfield      #7                  // Field config:Lorg/egovframe/rte/fdl/security/config/EgovSecurityConfig;
      69: invokevirtual #60                 // Method org/egovframe/rte/fdl/security/config/EgovSecurityConfig.getSqlHierarchicalRoles:()Ljava/lang/String;
      72: invokestatic  #51                 // Method org/springframework/util/StringUtils.hasText:(Ljava/lang/String;)Z
      75: ifeq          89
      78: aload_0
      79: aload_0
      80: getfield      #7                  // Field config:Lorg/egovframe/rte/fdl/security/config/EgovSecurityConfig;
      83: invokevirtual #60                 // Method org/egovframe/rte/fdl/security/config/EgovSecurityConfig.getSqlHierarchicalRoles:()Ljava/lang/String;
      86: putfield      #26                 // Field sqlHierarchicalRoles:Ljava/lang/String;
      89: return
    LineNumberTable:
      line 130: 0
      line 131: 7
      line 134: 17
      line 135: 30
      line 138: 41
      line 139: 54
      line 142: 65
      line 143: 78
      line 145: 89
    LocalVariableTable:
      Start  Length  Slot  Name   Signature
          0      90     0  this   Lorg/egovframe/rte/fdl/security/secureobject/impl/SecuredObjectDAO;

  public java.util.LinkedHashMap<java.lang.Object, java.util.List<org.springframework.security.access.ConfigAttribute>> getRolesAndResources(java.lang.String, java.lang.String);
    Code:
       0: ldc           #63                 // String url
       2: aload_1
       3: invokevirtual #65                 // Method java/lang/String.equals:(Ljava/lang/Object;)Z
       6: ifne          19
       9: new           #71                 // class java/lang/UnsupportedOperationException
      12: dup
      13: ldc           #73                 // String Only resourceType \'url\' is supported in Spring Security 6.x. Use @EnableMethodSecurity and @PreAuthorize for method-level authorization.
      15: invokespecial #75                 // Method java/lang/UnsupportedOperationException."<init>":(Ljava/lang/String;)V
      18: athrow
      19: new           #76                 // class java/util/LinkedHashMap
      22: dup
      23: invokespecial #78                 // Method java/util/LinkedHashMap."<init>":()V
      26: astore_3
      27: aload_0
      28: invokevirtual #79                 // Method getSqlRolesAndUrl:()Ljava/lang/String;
      31: astore        4
      33: aload_0
      34: getfield      #34                 // Field namedParameterJdbcTemplate:Lorg/springframework/jdbc/core/namedparam/NamedParameterJdbcTemplate;
      37: aload         4
      39: new           #80                 // class java/util/HashMap
      42: dup
      43: invokespecial #82                 // Method java/util/HashMap."<init>":()V
      46: invokevirtual #83                 // Method org/springframework/jdbc/core/namedparam/NamedParameterJdbcTemplate.queryForList:(Ljava/lang/String;Ljava/util/Map;)Ljava/util/List;
      49: astore        5
      51: aload         5
      53: invokeinterface #87,  1           // InterfaceMethod java/util/List.iterator:()Ljava/util/Iterator;
      58: astore        6
      60: aconst_null
      61: astore        8
      63: aload         6
      65: invokeinterface #93,  1           // InterfaceMethod java/util/Iterator.hasNext:()Z
      70: ifeq          291
      73: aload         6
      75: invokeinterface #99,  1           // InterfaceMethod java/util/Iterator.next:()Ljava/lang/Object;
      80: checkcast     #103                // class java/util/Map
      83: astore        7
      85: aload         7
      87: aload_1
      88: invokeinterface #105,  2          // InterfaceMethod java/util/Map.get:(Ljava/lang/Object;)Ljava/lang/Object;
      93: checkcast     #66                 // class java/lang/String
      96: astore        9
      98: aload_2
      99: ifnull        126
     102: aload_2
     103: ldc           #109                // String regex
     105: invokevirtual #111                // Method java/lang/String.equalsIgnoreCase:(Ljava/lang/String;)Z
     108: ifeq          126
     111: new           #114                // class org/egovframe/rte/fdl/security/secureobject/impl/SelfRegexRequestMatcher
     114: dup
     115: aload         9
     117: aconst_null
     118: invokespecial #116                // Method org/egovframe/rte/fdl/security/secureobject/impl/SelfRegexRequestMatcher."<init>":(Ljava/lang/String;Ljava/lang/String;)V
     121: astore        10
     123: goto          159
     126: aload_2
     127: ifnull        155
     130: aload_2
     131: ldc           #119                // String ciRegex
     133: invokevirtual #111                // Method java/lang/String.equalsIgnoreCase:(Ljava/lang/String;)Z
     136: ifeq          155
     139: new           #114                // class org/egovframe/rte/fdl/security/secureobject/impl/SelfRegexRequestMatcher
     142: dup
     143: aload         9
     145: aconst_null
     146: iconst_1
     147: invokespecial #121                // Method org/egovframe/rte/fdl/security/secureobject/impl/SelfRegexRequestMatcher."<init>":(Ljava/lang/String;Ljava/lang/String;Z)V
     150: astore        10
     152: goto          159
     155: aload         9
     157: astore        10
     159: new           #124                // class java/util/LinkedList
     162: dup
     163: invokespecial #126                // Method java/util/LinkedList."<init>":()V
     166: astore        11
     168: aload         8
     170: invokestatic  #127                // Method org/springframework/util/ObjectUtils.isEmpty:(Ljava/lang/Object;)Z
     173: ifne          248
     176: aload         9
     178: aload         8
     180: invokevirtual #65                 // Method java/lang/String.equals:(Ljava/lang/Object;)Z
     183: ifeq          248
     186: aload_3
     187: aload         10
     189: invokevirtual #132                // Method java/util/LinkedHashMap.get:(Ljava/lang/Object;)Ljava/lang/Object;
     192: checkcast     #88                 // class java/util/List
     195: astore        12
     197: aload         12
     199: invokeinterface #87,  1           // InterfaceMethod java/util/List.iterator:()Ljava/util/Iterator;
     204: astore        13
     206: aload         13
     208: invokeinterface #93,  1           // InterfaceMethod java/util/Iterator.hasNext:()Z
     213: ifeq          248
     216: aload         13
     218: invokeinterface #99,  1           // InterfaceMethod java/util/Iterator.next:()Ljava/lang/Object;
     223: checkcast     #133                // class org/springframework/security/access/ConfigAttribute
     226: astore        14
     228: aload         14
     230: checkcast     #135                // class org/springframework/security/access/SecurityConfig
     233: astore        15
     235: aload         11
     237: aload         15
     239: invokeinterface #137,  2          // InterfaceMethod java/util/List.add:(Ljava/lang/Object;)Z
     244: pop
     245: goto          206
     248: aload         11
     250: new           #135                // class org/springframework/security/access/SecurityConfig
     253: dup
     254: aload         7
     256: ldc           #140                // String authority
     258: invokeinterface #105,  2          // InterfaceMethod java/util/Map.get:(Ljava/lang/Object;)Ljava/lang/Object;
     263: checkcast     #66                 // class java/lang/String
     266: invokespecial #142                // Method org/springframework/security/access/SecurityConfig."<init>":(Ljava/lang/String;)V
     269: invokeinterface #137,  2          // InterfaceMethod java/util/List.add:(Ljava/lang/Object;)Z
     274: pop
     275: aload_3
     276: aload         10
     278: aload         11
     280: invokevirtual #143                // Method java/util/LinkedHashMap.put:(Ljava/lang/Object;Ljava/lang/Object;)Ljava/lang/Object;
     283: pop
     284: aload         9
     286: astore        8
     288: goto          63
     291: aload_3
     292: areturn
    LineNumberTable:
      line 152: 0
      line 153: 9
      line 156: 19
      line 157: 27
      line 159: 33
      line 161: 51
      line 163: 60
      line 166: 63
      line 167: 73
      line 168: 85
      line 170: 98
      line 171: 111
      line 172: 126
      line 173: 139
      line 175: 155
      line 178: 159
      line 183: 168
      line 184: 186
      line 185: 197
      line 186: 228
      line 187: 235
      line 188: 245
      line 191: 248
      line 195: 275
      line 198: 284
      line 199: 288
      line 201: 291
    LocalVariableTable:
      Start  Length  Slot  Name   Signature
        123       3    10 presentResource   Ljava/lang/Object;
        152       3    10 presentResource   Ljava/lang/Object;
        235      10    15 tempConfig   Lorg/springframework/security/access/SecurityConfig;
        228      17    14 configAttribute   Lorg/springframework/security/access/ConfigAttribute;
        197      51    12 preAuthList   Ljava/util/List;
        168     120    11 configList   Ljava/util/List;
         85     206     7 tempMap   Ljava/util/Map;
         98     193     9 presentResourceStr   Ljava/lang/String;
        159     132    10 presentResource   Ljava/lang/Object;
          0     293     0  this   Lorg/egovframe/rte/fdl/security/secureobject/impl/SecuredObjectDAO;
          0     293     1 resourceType   Ljava/lang/String;
          0     293     2 requestMatcherType   Ljava/lang/String;
         27     266     3 resourcesMap   Ljava/util/LinkedHashMap;
         33     260     4 sqlRolesAndResources   Ljava/lang/String;
         51     242     5 resultList   Ljava/util/List;
         60     233     6   itr   Ljava/util/Iterator;
         63     230     8 preResource   Ljava/lang/String;

  public java.util.LinkedHashMap<java.lang.Object, java.util.List<org.springframework.security.access.ConfigAttribute>> getRolesAndUrl(java.lang.String);
    Code:
       0: aload_0
       1: ldc           #63                 // String url
       3: aload_1
       4: invokevirtual #147                // Method getRolesAndResources:(Ljava/lang/String;Ljava/lang/String;)Ljava/util/LinkedHashMap;
       7: areturn
    LineNumberTable:
      line 205: 0
    LocalVariableTable:
      Start  Length  Slot  Name   Signature
          0       8     0  this   Lorg/egovframe/rte/fdl/security/secureobject/impl/SecuredObjectDAO;
          0       8     1 requestMatcherType   Ljava/lang/String;

  public java.util.List<org.springframework.security.access.ConfigAttribute> getRegexMatchedRequestMapping(java.lang.String);
    Code:
       0: new           #80                 // class java/util/HashMap
       3: dup
       4: invokespecial #82                 // Method java/util/HashMap."<init>":()V
       7: astore_2
       8: aload_2
       9: ldc           #63                 // String url
      11: aload_1
      12: invokeinterface #151,  3          // InterfaceMethod java/util/Map.put:(Ljava/lang/Object;Ljava/lang/Object;)Ljava/lang/Object;
      17: pop
      18: aload_0
      19: getfield      #34                 // Field namedParameterJdbcTemplate:Lorg/springframework/jdbc/core/namedparam/NamedParameterJdbcTemplate;
      22: aload_0
      23: invokevirtual #152                // Method getSqlRegexMatchedRequestMapping:()Ljava/lang/String;
      26: aload_2
      27: invokevirtual #83                 // Method org/springframework/jdbc/core/namedparam/NamedParameterJdbcTemplate.queryForList:(Ljava/lang/String;Ljava/util/Map;)Ljava/util/List;
      30: astore_3
      31: aload_3
      32: invokeinterface #87,  1           // InterfaceMethod java/util/List.iterator:()Ljava/util/Iterator;
      37: astore        4
      39: new           #124                // class java/util/LinkedList
      42: dup
      43: invokespecial #126                // Method java/util/LinkedList."<init>":()V
      46: astore        6
      48: aload         4
      50: invokeinterface #93,  1           // InterfaceMethod java/util/Iterator.hasNext:()Z
      55: ifeq          100
      58: aload         4
      60: invokeinterface #99,  1           // InterfaceMethod java/util/Iterator.next:()Ljava/lang/Object;
      65: checkcast     #103                // class java/util/Map
      68: astore        5
      70: aload         6
      72: new           #135                // class org/springframework/security/access/SecurityConfig
      75: dup
      76: aload         5
      78: ldc           #140                // String authority
      80: invokeinterface #105,  2          // InterfaceMethod java/util/Map.get:(Ljava/lang/Object;)Ljava/lang/Object;
      85: checkcast     #66                 // class java/lang/String
      88: invokespecial #142                // Method org/springframework/security/access/SecurityConfig."<init>":(Ljava/lang/String;)V
      91: invokeinterface #137,  2          // InterfaceMethod java/util/List.add:(Ljava/lang/Object;)Z
      96: pop
      97: goto          48
     100: aload         6
     102: areturn
    LineNumberTable:
      line 211: 0
      line 212: 8
      line 213: 18
      line 215: 31
      line 217: 39
      line 220: 48
      line 221: 58
      line 222: 70
      line 225: 100
    LocalVariableTable:
      Start  Length  Slot  Name   Signature
         70      30     5 tempMap   Ljava/util/Map;
          0     103     0  this   Lorg/egovframe/rte/fdl/security/secureobject/impl/SecuredObjectDAO;
          0     103     1   url   Ljava/lang/String;
          8      95     2 paramMap   Ljava/util/Map;
         31      72     3 resultList   Ljava/util/List;
         39      64     4   itr   Ljava/util/Iterator;
         48      55     6 configList   Ljava/util/List;

  public java.lang.String getHierarchicalRoles();
    Code:
       0: aload_0
       1: getfield      #34                 // Field namedParameterJdbcTemplate:Lorg/springframework/jdbc/core/namedparam/NamedParameterJdbcTemplate;
       4: aload_0
       5: invokevirtual #153                // Method getSqlHierarchicalRoles:()Ljava/lang/String;
       8: new           #80                 // class java/util/HashMap
      11: dup
      12: invokespecial #82                 // Method java/util/HashMap."<init>":()V
      15: invokevirtual #83                 // Method org/springframework/jdbc/core/namedparam/NamedParameterJdbcTemplate.queryForList:(Ljava/lang/String;Ljava/util/Map;)Ljava/util/List;
      18: astore_1
      19: aload_1
      20: invokeinterface #87,  1           // InterfaceMethod java/util/List.iterator:()Ljava/util/Iterator;
      25: astore_2
      26: new           #154                // class java/lang/StringBuilder
      29: dup
      30: invokespecial #156                // Method java/lang/StringBuilder."<init>":()V
      33: astore_3
      34: aload_2
      35: invokeinterface #93,  1           // InterfaceMethod java/util/Iterator.hasNext:()Z
      40: ifeq          99
      43: aload_2
      44: invokeinterface #99,  1           // InterfaceMethod java/util/Iterator.next:()Ljava/lang/Object;
      49: checkcast     #103                // class java/util/Map
      52: astore        4
      54: aload_3
      55: aload         4
      57: ldc           #157                // String child
      59: invokeinterface #105,  2          // InterfaceMethod java/util/Map.get:(Ljava/lang/Object;)Ljava/lang/Object;
      64: invokevirtual #159                // Method java/lang/StringBuilder.append:(Ljava/lang/Object;)Ljava/lang/StringBuilder;
      67: pop
      68: aload_3
      69: ldc           #163                // String  >
      71: invokevirtual #165                // Method java/lang/StringBuilder.append:(Ljava/lang/String;)Ljava/lang/StringBuilder;
      74: pop
      75: aload_3
      76: aload         4
      78: ldc           #168                // String parent
      80: invokeinterface #105,  2          // InterfaceMethod java/util/Map.get:(Ljava/lang/Object;)Ljava/lang/Object;
      85: invokevirtual #159                // Method java/lang/StringBuilder.append:(Ljava/lang/Object;)Ljava/lang/StringBuilder;
      88: pop
      89: aload_3
      90: ldc           #170                // String \n
      92: invokevirtual #165                // Method java/lang/StringBuilder.append:(Ljava/lang/String;)Ljava/lang/StringBuilder;
      95: pop
      96: goto          34
      99: aload_3
     100: invokevirtual #172                // Method java/lang/StringBuilder.toString:()Ljava/lang/String;
     103: areturn
    LineNumberTable:
      line 229: 0
      line 231: 19
      line 232: 26
      line 234: 34
      line 235: 43
      line 236: 54
      line 237: 68
      line 238: 75
      line 239: 89
      line 242: 99
    LocalVariableTable:
      Start  Length  Slot  Name   Signature
         54      45     4 tempMap   Ljava/util/Map;
          0     104     0  this   Lorg/egovframe/rte/fdl/security/secureobject/impl/SecuredObjectDAO;
         19      85     1 resultList   Ljava/util/List;
         26      78     2   itr   Ljava/util/Iterator;
         34      70     3 concatedRoles   Ljava/lang/StringBuilder;

  static {};
    Code:
       0: ldc           #8                  // class org/egovframe/rte/fdl/security/secureobject/impl/SecuredObjectDAO
       2: invokestatic  #175                // Method org/slf4j/LoggerFactory.getLogger:(Ljava/lang/Class;)Lorg/slf4j/Logger;
       5: putstatic     #181                // Field LOGGER:Lorg/slf4j/Logger;
       8: return
    LineNumberTable:
      line 54: 0
}
