Compiled from "EgovSecurityConfiguration.java"
public class org.egovframe.rte.fdl.security.config.EgovSecurityConfiguration {
  private java.lang.String securityConfigPath;

  private org.springframework.context.ApplicationContext applicationContext;

  private org.egovframe.rte.fdl.security.config.EgovSecurityConfig securityConfig;

  public org.egovframe.rte.fdl.security.config.EgovSecurityConfiguration();
    Code:
       0: aload_0
       1: invokespecial #1                  // Method java/lang/Object."<init>":()V
       4: return
    LineNumberTable:
      line 77: 0
    LocalVariableTable:
      Start  Length  Slot  Name   Signature
          0       5     0  this   Lorg/egovframe/rte/fdl/security/config/EgovSecurityConfiguration;

  public org.egovframe.rte.fdl.security.config.EgovSecurityConfigReader egovSecurityConfigReader(java.lang.String);
    Code:
       0: new           #7                  // class org/egovframe/rte/fdl/security/config/EgovSecurityConfigReader
       3: dup
       4: aload_1
       5: aload_0
       6: getfield      #9                  // Field applicationContext:Lorg/springframework/context/ApplicationContext;
       9: invokespecial #15                 // Method org/egovframe/rte/fdl/security/config/EgovSecurityConfigReader."<init>":(Ljava/lang/String;Lorg/springframework/core/io/ResourceLoader;)V
      12: areturn
    LineNumberTable:
      line 94: 0
    LocalVariableTable:
      Start  Length  Slot  Name   Signature
          0      13     0  this   Lorg/egovframe/rte/fdl/security/config/EgovSecurityConfiguration;
          0      13     1 securityConfigPath   Ljava/lang/String;

  public org.egovframe.rte.fdl.security.config.EgovSecurityConfig egovSecurityConfig(java.lang.String);
    Code:
       0: aload_0
       1: getfield      #18                 // Field securityConfig:Lorg/egovframe/rte/fdl/security/config/EgovSecurityConfig;
       4: ifnonnull     28
       7: new           #7                  // class org/egovframe/rte/fdl/security/config/EgovSecurityConfigReader
      10: dup
      11: aload_1
      12: aload_0
      13: getfield      #9                  // Field applicationContext:Lorg/springframework/context/ApplicationContext;
      16: invokespecial #15                 // Method org/egovframe/rte/fdl/security/config/EgovSecurityConfigReader."<init>":(Ljava/lang/String;Lorg/springframework/core/io/ResourceLoader;)V
      19: astore_2
      20: aload_0
      21: aload_2
      22: invokevirtual #22                 // Method org/egovframe/rte/fdl/security/config/EgovSecurityConfigReader.readConfig:()Lorg/egovframe/rte/fdl/security/config/EgovSecurityConfig;
      25: putfield      #18                 // Field securityConfig:Lorg/egovframe/rte/fdl/security/config/EgovSecurityConfig;
      28: aload_0
      29: getfield      #18                 // Field securityConfig:Lorg/egovframe/rte/fdl/security/config/EgovSecurityConfig;
      32: areturn
    LineNumberTable:
      line 100: 0
      line 101: 7
      line 102: 20
      line 104: 28
    LocalVariableTable:
      Start  Length  Slot  Name   Signature
         20       8     2 reader   Lorg/egovframe/rte/fdl/security/config/EgovSecurityConfigReader;
          0      33     0  this   Lorg/egovframe/rte/fdl/security/config/EgovSecurityConfiguration;
          0      33     1 securityConfigPath   Ljava/lang/String;

  private static java.util.List<org.springframework.security.web.util.matcher.RequestMatcher> buildPermitAllMatchers(java.lang.String, org.springframework.security.web.servlet.util.matcher.PathPatternRequestMatcher$Builder);
    Code:
       0: aload_0
       1: invokestatic  #26                 // Method org/springframework/util/ObjectUtils.isEmpty:(Ljava/lang/Object;)Z
       4: ifeq          15
       7: new           #32                 // class java/util/ArrayList
      10: dup
      11: invokespecial #34                 // Method java/util/ArrayList."<init>":()V
      14: areturn
      15: aload_0
      16: ldc           #35                 // String ,
      18: invokevirtual #37                 // Method java/lang/String.split:(Ljava/lang/String;)[Ljava/lang/String;
      21: astore_2
      22: new           #32                 // class java/util/ArrayList
      25: dup
      26: invokespecial #34                 // Method java/util/ArrayList."<init>":()V
      29: astore_3
      30: aload_2
      31: astore        4
      33: aload         4
      35: arraylength
      36: istore        5
      38: iconst_0
      39: istore        6
      41: iload         6
      43: iload         5
      45: if_icmpge     152
      48: aload         4
      50: iload         6
      52: aaload
      53: astore        7
      55: aload         7
      57: invokevirtual #43                 // Method java/lang/String.trim:()Ljava/lang/String;
      60: astore        8
      62: aload         8
      64: invokevirtual #47                 // Method java/lang/String.isEmpty:()Z
      67: ifeq          73
      70: goto          146
      73: aload         8
      75: ldc           #50                 // String \\A
      77: invokevirtual #52                 // Method java/lang/String.startsWith:(Ljava/lang/String;)Z
      80: ifne          113
      83: aload         8
      85: ldc           #56                 // String ^
      87: invokevirtual #52                 // Method java/lang/String.startsWith:(Ljava/lang/String;)Z
      90: ifne          113
      93: aload         8
      95: ldc           #58                 // String \\Z
      97: invokevirtual #60                 // Method java/lang/String.contains:(Ljava/lang/CharSequence;)Z
     100: ifne          113
     103: aload         8
     105: ldc           #64                 // String $
     107: invokevirtual #60                 // Method java/lang/String.contains:(Ljava/lang/CharSequence;)Z
     110: ifeq          133
     113: aload_3
     114: new           #66                 // class org/springframework/security/web/util/matcher/RegexRequestMatcher
     117: dup
     118: aload         8
     120: aconst_null
     121: invokespecial #68                 // Method org/springframework/security/web/util/matcher/RegexRequestMatcher."<init>":(Ljava/lang/String;Ljava/lang/String;)V
     124: invokeinterface #71,  2           // InterfaceMethod java/util/List.add:(Ljava/lang/Object;)Z
     129: pop
     130: goto          146
     133: aload_3
     134: aload_1
     135: aload         8
     137: invokevirtual #76                 // Method org/springframework/security/web/servlet/util/matcher/PathPatternRequestMatcher$Builder.matcher:(Ljava/lang/String;)Lorg/springframework/security/web/servlet/util/matcher/PathPatternRequestMatcher;
     140: invokeinterface #71,  2           // InterfaceMethod java/util/List.add:(Ljava/lang/Object;)Z
     145: pop
     146: iinc          6, 1
     149: goto          41
     152: aload_3
     153: areturn
    LineNumberTable:
      line 113: 0
      line 114: 15
      line 115: 22
      line 116: 30
      line 117: 55
      line 118: 62
      line 119: 73
      line 120: 113
      line 122: 133
      line 116: 146
      line 125: 152
    LocalVariableTable:
      Start  Length  Slot  Name   Signature
         62      84     8     p   Ljava/lang/String;
         55      91     7   raw   Ljava/lang/String;
          0     154     0   csv   Ljava/lang/String;
          0     154     1    pp   Lorg/springframework/security/web/servlet/util/matcher/PathPatternRequestMatcher$Builder;
         22     132     2 tokens   [Ljava/lang/String;
         30     124     3   out   Ljava/util/List;

  private static java.util.Map<org.springframework.security.web.util.matcher.RequestMatcher, java.util.Collection<java.lang.String>> loadUrlAuthorizationsFromDb(org.egovframe.rte.fdl.security.config.EgovSecurityConfig, org.springframework.jdbc.core.JdbcTemplate, org.springframework.security.web.servlet.util.matcher.PathPatternRequestMatcher$Builder);
    Code:
       0: new           #82                 // class java/util/LinkedHashMap
       3: dup
       4: invokespecial #84                 // Method java/util/LinkedHashMap."<init>":()V
       7: astore_3
       8: new           #32                 // class java/util/ArrayList
      11: dup
      12: invokespecial #34                 // Method java/util/ArrayList."<init>":()V
      15: astore        4
      17: aload_0
      18: invokevirtual #85                 // Method org/egovframe/rte/fdl/security/config/EgovSecurityConfig.getSqlRolesAndUrl:()Ljava/lang/String;
      21: invokestatic  #26                 // Method org/springframework/util/ObjectUtils.isEmpty:(Ljava/lang/Object;)Z
      24: ifne          43
      27: aload_1
      28: aload_0
      29: invokevirtual #85                 // Method org/egovframe/rte/fdl/security/config/EgovSecurityConfig.getSqlRolesAndUrl:()Ljava/lang/String;
      32: aload_3
      33: aload         4
      35: invokedynamic #90,  0             // InvokeDynamic #0:processRow:(Ljava/util/Map;Ljava/util/List;)Lorg/springframework/jdbc/core/RowCallbackHandler;
      40: invokevirtual #94                 // Method org/springframework/jdbc/core/JdbcTemplate.query:(Ljava/lang/String;Lorg/springframework/jdbc/core/RowCallbackHandler;)V
      43: aload         4
      45: invokedynamic #100,  0            // InvokeDynamic #1:compare:()Ljava/util/Comparator;
      50: invokeinterface #104,  2          // InterfaceMethod java/util/List.sort:(Ljava/util/Comparator;)V
      55: new           #82                 // class java/util/LinkedHashMap
      58: dup
      59: invokespecial #84                 // Method java/util/LinkedHashMap."<init>":()V
      62: astore        5
      64: aload         4
      66: invokeinterface #108,  1          // InterfaceMethod java/util/List.iterator:()Ljava/util/Iterator;
      71: astore        6
      73: aload         6
      75: invokeinterface #112,  1          // InterfaceMethod java/util/Iterator.hasNext:()Z
      80: ifeq          186
      83: aload         6
      85: invokeinterface #117,  1          // InterfaceMethod java/util/Iterator.next:()Ljava/lang/Object;
      90: checkcast     #38                 // class java/lang/String
      93: astore        7
      95: aload_3
      96: aload         7
      98: invokeinterface #121,  2          // InterfaceMethod java/util/Map.get:(Ljava/lang/Object;)Ljava/lang/Object;
     103: checkcast     #127                // class java/util/Collection
     106: astore        8
     108: aload         7
     110: ldc           #50                 // String \\A
     112: invokevirtual #52                 // Method java/lang/String.startsWith:(Ljava/lang/String;)Z
     115: ifne          148
     118: aload         7
     120: ldc           #56                 // String ^
     122: invokevirtual #52                 // Method java/lang/String.startsWith:(Ljava/lang/String;)Z
     125: ifne          148
     128: aload         7
     130: ldc           #58                 // String \\Z
     132: invokevirtual #60                 // Method java/lang/String.contains:(Ljava/lang/CharSequence;)Z
     135: ifne          148
     138: aload         7
     140: ldc           #64                 // String $
     142: invokevirtual #60                 // Method java/lang/String.contains:(Ljava/lang/CharSequence;)Z
     145: ifeq          163
     148: new           #66                 // class org/springframework/security/web/util/matcher/RegexRequestMatcher
     151: dup
     152: aload         7
     154: aconst_null
     155: invokespecial #68                 // Method org/springframework/security/web/util/matcher/RegexRequestMatcher."<init>":(Ljava/lang/String;Ljava/lang/String;)V
     158: astore        9
     160: goto          171
     163: aload_2
     164: aload         7
     166: invokevirtual #76                 // Method org/springframework/security/web/servlet/util/matcher/PathPatternRequestMatcher$Builder.matcher:(Ljava/lang/String;)Lorg/springframework/security/web/servlet/util/matcher/PathPatternRequestMatcher;
     169: astore        9
     171: aload         5
     173: aload         9
     175: aload         8
     177: invokeinterface #129,  3          // InterfaceMethod java/util/Map.put:(Ljava/lang/Object;Ljava/lang/Object;)Ljava/lang/Object;
     182: pop
     183: goto          73
     186: aload         5
     188: areturn
    LineNumberTable:
      line 137: 0
      line 140: 8
      line 142: 17
      line 143: 27
      line 158: 43
      line 166: 55
      line 167: 64
      line 168: 95
      line 171: 108
      line 172: 148
      line 174: 163
      line 176: 171
      line 177: 183
      line 179: 186
    LocalVariableTable:
      Start  Length  Slot  Name   Signature
        160       3     9 matcher   Lorg/springframework/security/web/util/matcher/RequestMatcher;
        108      75     8 authorities   Ljava/util/Collection;
        171      12     9 matcher   Lorg/springframework/security/web/util/matcher/RequestMatcher;
         95      88     7   url   Ljava/lang/String;
          0     189     0 props   Lorg/egovframe/rte/fdl/security/config/EgovSecurityConfig;
          0     189     1  jdbc   Lorg/springframework/jdbc/core/JdbcTemplate;
          0     189     2    pp   Lorg/springframework/security/web/servlet/util/matcher/PathPatternRequestMatcher$Builder;
          8     181     3 urlToAuthorities   Ljava/util/Map;
         17     172     4 urlOrder   Ljava/util/List;
         64     125     5 result   Ljava/util/Map;

  private static int calculateUrlSpecificity(java.lang.String);
    Code:
       0: iconst_0
       1: istore_1
       2: iload_1
       3: aload_0
       4: invokevirtual #133                // Method java/lang/String.length:()I
       7: bipush        10
       9: imul
      10: iadd
      11: istore_1
      12: iload_1
      13: aload_0
      14: ldc           #137                // String \\*
      16: invokevirtual #37                 // Method java/lang/String.split:(Ljava/lang/String;)[Ljava/lang/String;
      19: arraylength
      20: iconst_1
      21: isub
      22: bipush        100
      24: imul
      25: isub
      26: istore_1
      27: iload_1
      28: aload_0
      29: ldc           #139                // String \\.\\*
      31: invokevirtual #37                 // Method java/lang/String.split:(Ljava/lang/String;)[Ljava/lang/String;
      34: arraylength
      35: iconst_1
      36: isub
      37: bipush        50
      39: imul
      40: isub
      41: istore_1
      42: iload_1
      43: aload_0
      44: ldc           #141                // String /
      46: invokevirtual #37                 // Method java/lang/String.split:(Ljava/lang/String;)[Ljava/lang/String;
      49: arraylength
      50: iconst_5
      51: imul
      52: iadd
      53: istore_1
      54: iload_1
      55: ireturn
    LineNumberTable:
      line 186: 0
      line 189: 2
      line 192: 12
      line 193: 27
      line 196: 42
      line 198: 54
    LocalVariableTable:
      Start  Length  Slot  Name   Signature
          0      56     0 urlPattern   Ljava/lang/String;
          2      54     1 specificity   I

  public org.springframework.security.crypto.password.PasswordEncoder passwordEncoder(org.egovframe.rte.fdl.security.config.EgovSecurityConfig);
    Code:
       0: aload_1
       1: ifnull        11
       4: aload_1
       5: invokevirtual #143                // Method org/egovframe/rte/fdl/security/config/EgovSecurityConfig.getHash:()Ljava/lang/String;
       8: goto          12
      11: aconst_null
      12: astore_2
      13: aload_2
      14: ifnull        27
      17: aload_2
      18: invokevirtual #43                 // Method java/lang/String.trim:()Ljava/lang/String;
      21: invokevirtual #47                 // Method java/lang/String.isEmpty:()Z
      24: ifeq          32
      27: ldc           #146                // String sha-256
      29: goto          39
      32: aload_2
      33: invokevirtual #43                 // Method java/lang/String.trim:()Ljava/lang/String;
      36: invokevirtual #148                // Method java/lang/String.toLowerCase:()Ljava/lang/String;
      39: astore_3
      40: aload_1
      41: ifnull        55
      44: aload_1
      45: invokevirtual #151                // Method org/egovframe/rte/fdl/security/config/EgovSecurityConfig.isHashBase64:()Z
      48: ifeq          55
      51: iconst_1
      52: goto          56
      55: iconst_0
      56: istore        4
      58: aload_3
      59: invokevirtual #148                // Method java/lang/String.toLowerCase:()Ljava/lang/String;
      62: astore        5
      64: iconst_m1
      65: istore        6
      67: aload         5
      69: invokevirtual #154                // Method java/lang/String.hashCode:()I
      72: lookupswitch  { // 4

                107902: 164

               3316647: 148

               3387234: 132

            1973234167: 116
               default: 177
          }
     116: aload         5
     118: ldc           #157                // String plaintext
     120: invokevirtual #159                // Method java/lang/String.equals:(Ljava/lang/Object;)Z
     123: ifeq          177
     126: iconst_0
     127: istore        6
     129: goto          177
     132: aload         5
     134: ldc           #162                // String noop
     136: invokevirtual #159                // Method java/lang/String.equals:(Ljava/lang/Object;)Z
     139: ifeq          177
     142: iconst_1
     143: istore        6
     145: goto          177
     148: aload         5
     150: ldc           #164                // String ldap
     152: invokevirtual #159                // Method java/lang/String.equals:(Ljava/lang/Object;)Z
     155: ifeq          177
     158: iconst_2
     159: istore        6
     161: goto          177
     164: aload         5
     166: ldc           #166                // String md5
     168: invokevirtual #159                // Method java/lang/String.equals:(Ljava/lang/Object;)Z
     171: ifeq          177
     174: iconst_3
     175: istore        6
     177: iload         6
     179: tableswitch   { // 0 to 3

                     0: 208

                     1: 208

                     2: 212

                     3: 220
               default: 241
          }
     208: invokestatic  #168                // Method org/springframework/security/crypto/password/NoOpPasswordEncoder.getInstance:()Lorg/springframework/security/crypto/password/PasswordEncoder;
     211: areturn
     212: new           #174                // class org/springframework/security/crypto/password/LdapShaPasswordEncoder
     215: dup
     216: invokespecial #176                // Method org/springframework/security/crypto/password/LdapShaPasswordEncoder."<init>":()V
     219: areturn
     220: new           #177                // class org/springframework/security/crypto/password/MessageDigestPasswordEncoder
     223: dup
     224: ldc           #179                // String MD5
     226: invokespecial #181                // Method org/springframework/security/crypto/password/MessageDigestPasswordEncoder."<init>":(Ljava/lang/String;)V
     229: astore        7
     231: aload         7
     233: iload         4
     235: invokevirtual #184                // Method org/springframework/security/crypto/password/MessageDigestPasswordEncoder.setEncodeHashAsBase64:(Z)V
     238: aload         7
     240: areturn
     241: aload_3
     242: ldc           #188                // String sha
     244: invokevirtual #52                 // Method java/lang/String.startsWith:(Ljava/lang/String;)Z
     247: ifeq          298
     250: aload_3
     251: ldc           #190                // String -
     253: ldc           #192                // String
     255: invokevirtual #194                // Method java/lang/String.replace:(Ljava/lang/CharSequence;Ljava/lang/CharSequence;)Ljava/lang/String;
     258: invokevirtual #198                // Method java/lang/String.toUpperCase:()Ljava/lang/String;
     261: astore        8
     263: ldc           #201                // String SHA
     265: aload         8
     267: invokevirtual #159                // Method java/lang/String.equals:(Ljava/lang/Object;)Z
     270: ifeq          277
     273: ldc           #203                // String SHA-256
     275: astore        8
     277: new           #177                // class org/springframework/security/crypto/password/MessageDigestPasswordEncoder
     280: dup
     281: aload         8
     283: invokespecial #181                // Method org/springframework/security/crypto/password/MessageDigestPasswordEncoder."<init>":(Ljava/lang/String;)V
     286: astore        9
     288: aload         9
     290: iload         4
     292: invokevirtual #184                // Method org/springframework/security/crypto/password/MessageDigestPasswordEncoder.setEncodeHashAsBase64:(Z)V
     295: aload         9
     297: areturn
     298: new           #205                // class org/springframework/security/crypto/bcrypt/BCryptPasswordEncoder
     301: dup
     302: invokespecial #207                // Method org/springframework/security/crypto/bcrypt/BCryptPasswordEncoder."<init>":()V
     305: areturn
    LineNumberTable:
      line 203: 0
      line 204: 13
      line 205: 40
      line 206: 58
      line 209: 208
      line 211: 212
      line 213: 220
      line 214: 231
      line 215: 238
      line 217: 241
      line 218: 250
      line 219: 263
      line 220: 277
      line 221: 288
      line 222: 295
      line 225: 298
    LocalVariableTable:
      Start  Length  Slot  Name   Signature
        231      10     7 md5Encoder   Lorg/springframework/security/crypto/password/MessageDigestPasswordEncoder;
        263      35     8 algorithm   Ljava/lang/String;
        288      10     9 shaEncoder   Lorg/springframework/security/crypto/password/MessageDigestPasswordEncoder;
          0     306     0  this   Lorg/egovframe/rte/fdl/security/config/EgovSecurityConfiguration;
          0     306     1 securityConfig   Lorg/egovframe/rte/fdl/security/config/EgovSecurityConfig;
         13     293     2 rawHash   Ljava/lang/String;
         40     266     3 securityHash   Ljava/lang/String;
         58     248     4 securityHashBase64   Z

  public org.egovframe.rte.fdl.security.bean.DataSourceFactoryBean securityDataSourceFactoryBean(org.egovframe.rte.fdl.security.config.EgovSecurityConfig);
    Code:
       0: new           #208                // class org/egovframe/rte/fdl/security/bean/DataSourceFactoryBean
       3: dup
       4: aload_1
       5: invokespecial #210                // Method org/egovframe/rte/fdl/security/bean/DataSourceFactoryBean."<init>":(Lorg/egovframe/rte/fdl/security/config/EgovSecurityConfig;)V
       8: areturn
    LineNumberTable:
      line 231: 0
    LocalVariableTable:
      Start  Length  Slot  Name   Signature
          0       9     0  this   Lorg/egovframe/rte/fdl/security/config/EgovSecurityConfiguration;
          0       9     1 securityConfig   Lorg/egovframe/rte/fdl/security/config/EgovSecurityConfig;

  public org.springframework.security.authentication.AuthenticationManager authenticationManager(org.egovframe.rte.fdl.security.config.EgovSecurityConfig);
    Code:
       0: new           #213                // class org/springframework/security/authentication/dao/DaoAuthenticationProvider
       3: dup
       4: invokespecial #215                // Method org/springframework/security/authentication/dao/DaoAuthenticationProvider."<init>":()V
       7: astore_2
       8: aload_2
       9: aload_0
      10: aload_1
      11: invokevirtual #216                // Method jdbcUserService:(Lorg/egovframe/rte/fdl/security/config/EgovSecurityConfig;)Lorg/egovframe/rte/fdl/security/userdetails/jdbc/EgovJdbcUserDetailsManager;
      14: invokevirtual #220                // Method org/springframework/security/authentication/dao/DaoAuthenticationProvider.setUserDetailsService:(Lorg/springframework/security/core/userdetails/UserDetailsService;)V
      17: aload_2
      18: aload_0
      19: aload_1
      20: invokevirtual #224                // Method passwordEncoder:(Lorg/egovframe/rte/fdl/security/config/EgovSecurityConfig;)Lorg/springframework/security/crypto/password/PasswordEncoder;
      23: invokevirtual #228                // Method org/springframework/security/authentication/dao/DaoAuthenticationProvider.setPasswordEncoder:(Lorg/springframework/security/crypto/password/PasswordEncoder;)V
      26: new           #232                // class org/springframework/security/access/hierarchicalroles/RoleHierarchyAuthoritiesMapper
      29: dup
      30: aload_0
      31: aload_1
      32: invokevirtual #234                // Method roleHierarchy:(Lorg/egovframe/rte/fdl/security/config/EgovSecurityConfig;)Lorg/springframework/security/access/hierarchicalroles/RoleHierarchy;
      35: invokespecial #238                // Method org/springframework/security/access/hierarchicalroles/RoleHierarchyAuthoritiesMapper."<init>":(Lorg/springframework/security/access/hierarchicalroles/RoleHierarchy;)V
      38: astore_3
      39: aload_2
      40: aload_3
      41: invokevirtual #241                // Method org/springframework/security/authentication/dao/DaoAuthenticationProvider.setAuthoritiesMapper:(Lorg/springframework/security/core/authority/mapping/GrantedAuthoritiesMapper;)V
      44: new           #245                // class org/springframework/security/authentication/ProviderManager
      47: dup
      48: iconst_1
      49: anewarray     #247                // class org/springframework/security/authentication/AuthenticationProvider
      52: dup
      53: iconst_0
      54: aload_2
      55: aastore
      56: invokespecial #249                // Method org/springframework/security/authentication/ProviderManager."<init>":([Lorg/springframework/security/authentication/AuthenticationProvider;)V
      59: areturn
    LineNumberTable:
      line 236: 0
      line 237: 8
      line 238: 17
      line 240: 26
      line 241: 39
      line 243: 44
    LocalVariableTable:
      Start  Length  Slot  Name   Signature
          0      60     0  this   Lorg/egovframe/rte/fdl/security/config/EgovSecurityConfiguration;
          0      60     1 securityConfig   Lorg/egovframe/rte/fdl/security/config/EgovSecurityConfig;
          8      52     2 provider   Lorg/springframework/security/authentication/dao/DaoAuthenticationProvider;
         39      21     3 mapper   Lorg/springframework/security/core/authority/mapping/GrantedAuthoritiesMapper;

  public org.egovframe.rte.fdl.security.userdetails.jdbc.EgovJdbcUserDetailsManager jdbcUserService(org.egovframe.rte.fdl.security.config.EgovSecurityConfig);
    Code:
       0: new           #252                // class org/egovframe/rte/fdl/security/userdetails/jdbc/EgovJdbcUserDetailsManager
       3: dup
       4: invokespecial #254                // Method org/egovframe/rte/fdl/security/userdetails/jdbc/EgovJdbcUserDetailsManager."<init>":()V
       7: astore_2
       8: aload_2
       9: aload_0
      10: aload_1
      11: invokevirtual #255                // Method securityDataSourceFactoryBean:(Lorg/egovframe/rte/fdl/security/config/EgovSecurityConfig;)Lorg/egovframe/rte/fdl/security/bean/DataSourceFactoryBean;
      14: invokevirtual #259                // Method org/egovframe/rte/fdl/security/bean/DataSourceFactoryBean.getObject:()Ljavax/sql/DataSource;
      17: invokevirtual #263                // Method org/egovframe/rte/fdl/security/userdetails/jdbc/EgovJdbcUserDetailsManager.setDataSource:(Ljavax/sql/DataSource;)V
      20: aload_2
      21: aload_0
      22: aload_1
      23: invokevirtual #267                // Method usersQueryFactoryBean:(Lorg/egovframe/rte/fdl/security/config/EgovSecurityConfig;)Lorg/egovframe/rte/fdl/security/bean/UsersQueryFactoryBean;
      26: invokevirtual #271                // Method org/egovframe/rte/fdl/security/bean/UsersQueryFactoryBean.getObject:()Ljava/lang/String;
      29: invokevirtual #275                // Method org/egovframe/rte/fdl/security/userdetails/jdbc/EgovJdbcUserDetailsManager.setUsersByUsernameQuery:(Ljava/lang/String;)V
      32: aload_2
      33: aload_0
      34: aload_1
      35: invokevirtual #278                // Method authoritiesQueryFactoryBean:(Lorg/egovframe/rte/fdl/security/config/EgovSecurityConfig;)Lorg/egovframe/rte/fdl/security/bean/AuthoritiesQueryFactoryBean;
      38: invokevirtual #282                // Method org/egovframe/rte/fdl/security/bean/AuthoritiesQueryFactoryBean.getObject:()Ljava/lang/String;
      41: invokevirtual #285                // Method org/egovframe/rte/fdl/security/userdetails/jdbc/EgovJdbcUserDetailsManager.setAuthoritiesByUsernameQuery:(Ljava/lang/String;)V
      44: aload_2
      45: aload_0
      46: aload_1
      47: invokevirtual #288                // Method mapClassFactoryBean:(Lorg/egovframe/rte/fdl/security/config/EgovSecurityConfig;)Lorg/egovframe/rte/fdl/security/bean/MapClassFactoryBean;
      50: invokevirtual #292                // Method org/egovframe/rte/fdl/security/bean/MapClassFactoryBean.getObject:()Ljava/lang/String;
      53: invokevirtual #295                // Method org/egovframe/rte/fdl/security/userdetails/jdbc/EgovJdbcUserDetailsManager.setMapClass:(Ljava/lang/String;)V
      56: aload_2
      57: aload_0
      58: aload_1
      59: invokevirtual #234                // Method roleHierarchy:(Lorg/egovframe/rte/fdl/security/config/EgovSecurityConfig;)Lorg/springframework/security/access/hierarchicalroles/RoleHierarchy;
      62: invokevirtual #298                // Method org/egovframe/rte/fdl/security/userdetails/jdbc/EgovJdbcUserDetailsManager.setRoleHierarchy:(Lorg/springframework/security/access/hierarchicalroles/RoleHierarchy;)V
      65: aload_2
      66: areturn
    LineNumberTable:
      line 251: 0
      line 252: 8
      line 253: 20
      line 254: 32
      line 255: 44
      line 256: 56
      line 257: 65
    LocalVariableTable:
      Start  Length  Slot  Name   Signature
          0      67     0  this   Lorg/egovframe/rte/fdl/security/config/EgovSecurityConfiguration;
          0      67     1 securityConfig   Lorg/egovframe/rte/fdl/security/config/EgovSecurityConfig;
          8      59     2 service   Lorg/egovframe/rte/fdl/security/userdetails/jdbc/EgovJdbcUserDetailsManager;

  public org.egovframe.rte.fdl.security.bean.UsersQueryFactoryBean usersQueryFactoryBean(org.egovframe.rte.fdl.security.config.EgovSecurityConfig);
    Code:
       0: new           #272                // class org/egovframe/rte/fdl/security/bean/UsersQueryFactoryBean
       3: dup
       4: aload_1
       5: invokespecial #301                // Method org/egovframe/rte/fdl/security/bean/UsersQueryFactoryBean."<init>":(Lorg/egovframe/rte/fdl/security/config/EgovSecurityConfig;)V
       8: areturn
    LineNumberTable:
      line 262: 0
    LocalVariableTable:
      Start  Length  Slot  Name   Signature
          0       9     0  this   Lorg/egovframe/rte/fdl/security/config/EgovSecurityConfiguration;
          0       9     1 securityConfig   Lorg/egovframe/rte/fdl/security/config/EgovSecurityConfig;

  public org.egovframe.rte.fdl.security.bean.AuthoritiesQueryFactoryBean authoritiesQueryFactoryBean(org.egovframe.rte.fdl.security.config.EgovSecurityConfig);
    Code:
       0: new           #283                // class org/egovframe/rte/fdl/security/bean/AuthoritiesQueryFactoryBean
       3: dup
       4: aload_1
       5: invokespecial #302                // Method org/egovframe/rte/fdl/security/bean/AuthoritiesQueryFactoryBean."<init>":(Lorg/egovframe/rte/fdl/security/config/EgovSecurityConfig;)V
       8: areturn
    LineNumberTable:
      line 267: 0
    LocalVariableTable:
      Start  Length  Slot  Name   Signature
          0       9     0  this   Lorg/egovframe/rte/fdl/security/config/EgovSecurityConfiguration;
          0       9     1 securityConfig   Lorg/egovframe/rte/fdl/security/config/EgovSecurityConfig;

  public org.egovframe.rte.fdl.security.bean.MapClassFactoryBean mapClassFactoryBean(org.egovframe.rte.fdl.security.config.EgovSecurityConfig);
    Code:
       0: new           #293                // class org/egovframe/rte/fdl/security/bean/MapClassFactoryBean
       3: dup
       4: aload_1
       5: invokespecial #303                // Method org/egovframe/rte/fdl/security/bean/MapClassFactoryBean."<init>":(Lorg/egovframe/rte/fdl/security/config/EgovSecurityConfig;)V
       8: astore_2
       9: aload_2
      10: ldc_w         #304                // String org.egovframe.rte.fdl.security.userdetails.DefaultMapUserDetailsMapping
      13: invokevirtual #306                // Method org/egovframe/rte/fdl/security/bean/MapClassFactoryBean.setDefaultMapClass:(Ljava/lang/String;)V
      16: aload_2
      17: areturn
    LineNumberTable:
      line 272: 0
      line 273: 9
      line 274: 16
    LocalVariableTable:
      Start  Length  Slot  Name   Signature
          0      18     0  this   Lorg/egovframe/rte/fdl/security/config/EgovSecurityConfiguration;
          0      18     1 securityConfig   Lorg/egovframe/rte/fdl/security/config/EgovSecurityConfig;
          9       9     2  bean   Lorg/egovframe/rte/fdl/security/bean/MapClassFactoryBean;

  public org.springframework.security.access.hierarchicalroles.RoleHierarchy roleHierarchy(org.egovframe.rte.fdl.security.config.EgovSecurityConfig);
    Code:
       0: aload_1
       1: invokevirtual #309                // Method org/egovframe/rte/fdl/security/config/EgovSecurityConfig.getSqlHierarchicalRoles:()Ljava/lang/String;
       4: invokestatic  #26                 // Method org/springframework/util/ObjectUtils.isEmpty:(Ljava/lang/Object;)Z
       7: ifeq          12
      10: aconst_null
      11: areturn
      12: new           #312                // class org/springframework/security/access/hierarchicalroles/RoleHierarchyImpl
      15: dup
      16: invokespecial #314                // Method org/springframework/security/access/hierarchicalroles/RoleHierarchyImpl."<init>":()V
      19: astore_2
      20: aload_2
      21: aload_0
      22: aload_1
      23: invokevirtual #315                // Method hierarchyStrings:(Lorg/egovframe/rte/fdl/security/config/EgovSecurityConfig;)Ljava/lang/String;
      26: invokevirtual #319                // Method org/springframework/security/access/hierarchicalroles/RoleHierarchyImpl.setHierarchy:(Ljava/lang/String;)V
      29: aload_2
      30: areturn
    LineNumberTable:
      line 283: 0
      line 284: 12
      line 285: 20
      line 286: 29
    LocalVariableTable:
      Start  Length  Slot  Name   Signature
          0      31     0  this   Lorg/egovframe/rte/fdl/security/config/EgovSecurityConfiguration;
          0      31     1 securityConfig   Lorg/egovframe/rte/fdl/security/config/EgovSecurityConfig;
         20      11     2 hierarchy   Lorg/springframework/security/access/hierarchicalroles/RoleHierarchyImpl;

  public java.lang.String hierarchyStrings(org.egovframe.rte.fdl.security.config.EgovSecurityConfig);
    Code:
       0: new           #322                // class org/egovframe/rte/fdl/security/userdetails/hierarchicalroles/HierarchyStringsFactoryBean
       3: dup
       4: aload_1
       5: invokespecial #324                // Method org/egovframe/rte/fdl/security/userdetails/hierarchicalroles/HierarchyStringsFactoryBean."<init>":(Lorg/egovframe/rte/fdl/security/config/EgovSecurityConfig;)V
       8: astore_2
       9: aload_2
      10: aload_0
      11: aload_1
      12: invokevirtual #325                // Method securedObjectService:(Lorg/egovframe/rte/fdl/security/config/EgovSecurityConfig;)Lorg/egovframe/rte/fdl/security/secureobject/impl/SecuredObjectServiceImpl;
      15: invokevirtual #329                // Method org/egovframe/rte/fdl/security/userdetails/hierarchicalroles/HierarchyStringsFactoryBean.setSecuredObjectService:(Lorg/egovframe/rte/fdl/security/secureobject/EgovSecuredObjectService;)V
      18: aload_2
      19: invokevirtual #333                // Method org/egovframe/rte/fdl/security/userdetails/hierarchicalroles/HierarchyStringsFactoryBean.getObject:()Ljava/lang/String;
      22: areturn
    LineNumberTable:
      line 291: 0
      line 292: 9
      line 293: 18
    LocalVariableTable:
      Start  Length  Slot  Name   Signature
          0      23     0  this   Lorg/egovframe/rte/fdl/security/config/EgovSecurityConfiguration;
          0      23     1 securityConfig   Lorg/egovframe/rte/fdl/security/config/EgovSecurityConfig;
          9      14     2  bean   Lorg/egovframe/rte/fdl/security/userdetails/hierarchicalroles/HierarchyStringsFactoryBean;

  public org.egovframe.rte.fdl.security.secureobject.impl.SecuredObjectServiceImpl securedObjectService(org.egovframe.rte.fdl.security.config.EgovSecurityConfig);
    Code:
       0: new           #334                // class org/egovframe/rte/fdl/security/secureobject/impl/SecuredObjectServiceImpl
       3: dup
       4: aload_1
       5: invokespecial #336                // Method org/egovframe/rte/fdl/security/secureobject/impl/SecuredObjectServiceImpl."<init>":(Lorg/egovframe/rte/fdl/security/config/EgovSecurityConfig;)V
       8: astore_2
       9: aload_2
      10: aload_0
      11: aload_1
      12: invokevirtual #337                // Method securedObjectDAO:(Lorg/egovframe/rte/fdl/security/config/EgovSecurityConfig;)Lorg/egovframe/rte/fdl/security/secureobject/impl/SecuredObjectDAO;
      15: invokevirtual #341                // Method org/egovframe/rte/fdl/security/secureobject/impl/SecuredObjectServiceImpl.setSecuredObjectDAO:(Lorg/egovframe/rte/fdl/security/secureobject/impl/SecuredObjectDAO;)V
      18: aload_2
      19: areturn
    LineNumberTable:
      line 298: 0
      line 299: 9
      line 300: 18
    LocalVariableTable:
      Start  Length  Slot  Name   Signature
          0      20     0  this   Lorg/egovframe/rte/fdl/security/config/EgovSecurityConfiguration;
          0      20     1 securityConfig   Lorg/egovframe/rte/fdl/security/config/EgovSecurityConfig;
          9      11     2 service   Lorg/egovframe/rte/fdl/security/secureobject/impl/SecuredObjectServiceImpl;

  public org.egovframe.rte.fdl.security.secureobject.impl.SecuredObjectDAO securedObjectDAO(org.egovframe.rte.fdl.security.config.EgovSecurityConfig);
    Code:
       0: new           #345                // class org/egovframe/rte/fdl/security/secureobject/impl/SecuredObjectDAO
       3: dup
       4: aload_1
       5: invokespecial #347                // Method org/egovframe/rte/fdl/security/secureobject/impl/SecuredObjectDAO."<init>":(Lorg/egovframe/rte/fdl/security/config/EgovSecurityConfig;)V
       8: astore_2
       9: aload_2
      10: aload_0
      11: aload_1
      12: invokevirtual #255                // Method securityDataSourceFactoryBean:(Lorg/egovframe/rte/fdl/security/config/EgovSecurityConfig;)Lorg/egovframe/rte/fdl/security/bean/DataSourceFactoryBean;
      15: invokevirtual #259                // Method org/egovframe/rte/fdl/security/bean/DataSourceFactoryBean.getObject:()Ljavax/sql/DataSource;
      18: invokevirtual #348                // Method org/egovframe/rte/fdl/security/secureobject/impl/SecuredObjectDAO.setDataSource:(Ljavax/sql/DataSource;)V
      21: aload_2
      22: areturn
    LineNumberTable:
      line 305: 0
      line 306: 9
      line 307: 21
    LocalVariableTable:
      Start  Length  Slot  Name   Signature
          0      23     0  this   Lorg/egovframe/rte/fdl/security/config/EgovSecurityConfiguration;
          0      23     1 securityConfig   Lorg/egovframe/rte/fdl/security/config/EgovSecurityConfig;
          9      14     2   dao   Lorg/egovframe/rte/fdl/security/secureobject/impl/SecuredObjectDAO;

  public org.egovframe.rte.fdl.security.bean.UrlResourcesMapFactoryBean requestMap(org.egovframe.rte.fdl.security.config.EgovSecurityConfig);
    Code:
       0: new           #349                // class org/egovframe/rte/fdl/security/bean/UrlResourcesMapFactoryBean
       3: dup
       4: invokespecial #351                // Method org/egovframe/rte/fdl/security/bean/UrlResourcesMapFactoryBean."<init>":()V
       7: astore_2
       8: aload_2
       9: aload_0
      10: aload_1
      11: invokevirtual #325                // Method securedObjectService:(Lorg/egovframe/rte/fdl/security/config/EgovSecurityConfig;)Lorg/egovframe/rte/fdl/security/secureobject/impl/SecuredObjectServiceImpl;
      14: invokevirtual #352                // Method org/egovframe/rte/fdl/security/bean/UrlResourcesMapFactoryBean.setSecuredObjectService:(Lorg/egovframe/rte/fdl/security/secureobject/EgovSecuredObjectService;)V
      17: aload_2
      18: astore_3
      19: aload_3
      20: invokevirtual #353                // Method org/egovframe/rte/fdl/security/bean/UrlResourcesMapFactoryBean.getObject:()Ljava/util/LinkedHashMap;
      23: invokestatic  #356                // Method org/egovframe/rte/fdl/security/config/EgovSecurityMetadataCache.setRequestMap:(Ljava/util/Map;)V
      26: aload_3
      27: areturn
    LineNumberTable:
      line 312: 0
      line 313: 8
      line 314: 17
      line 315: 19
      line 316: 26
    LocalVariableTable:
      Start  Length  Slot  Name   Signature
          0      28     0  this   Lorg/egovframe/rte/fdl/security/config/EgovSecurityConfiguration;
          0      28     1 securityConfig   Lorg/egovframe/rte/fdl/security/config/EgovSecurityConfig;
          8      20     2   map   Lorg/egovframe/rte/fdl/security/bean/UrlResourcesMapFactoryBean;
         19       9     3 resultMap   Lorg/egovframe/rte/fdl/security/bean/UrlResourcesMapFactoryBean;

  public org.springframework.security.web.authentication.UsernamePasswordAuthenticationFilter usernamePasswordAuthenticationFilter(org.egovframe.rte.fdl.security.config.EgovSecurityConfig);
    Code:
       0: new           #362                // class org/springframework/security/web/authentication/UsernamePasswordAuthenticationFilter
       3: dup
       4: invokespecial #364                // Method org/springframework/security/web/authentication/UsernamePasswordAuthenticationFilter."<init>":()V
       7: astore_2
       8: aload_2
       9: aload_0
      10: aload_1
      11: invokevirtual #365                // Method authenticationManager:(Lorg/egovframe/rte/fdl/security/config/EgovSecurityConfig;)Lorg/springframework/security/authentication/AuthenticationManager;
      14: invokevirtual #369                // Method org/springframework/security/web/authentication/UsernamePasswordAuthenticationFilter.setAuthenticationManager:(Lorg/springframework/security/authentication/AuthenticationManager;)V
      17: aload_2
      18: areturn
    LineNumberTable:
      line 321: 0
      line 322: 8
      line 323: 17
    LocalVariableTable:
      Start  Length  Slot  Name   Signature
          0      19     0  this   Lorg/egovframe/rte/fdl/security/config/EgovSecurityConfiguration;
          0      19     1 securityConfig   Lorg/egovframe/rte/fdl/security/config/EgovSecurityConfig;
          8      11     2 filter   Lorg/springframework/security/web/authentication/UsernamePasswordAuthenticationFilter;

  public org.egovframe.rte.fdl.security.bean.EgovLoginFailHandler egovLoginFailHandler(org.egovframe.rte.fdl.security.config.EgovSecurityConfig);
    Code:
       0: new           #373                // class org/egovframe/rte/fdl/security/bean/EgovLoginFailHandler
       3: dup
       4: aload_1
       5: invokespecial #375                // Method org/egovframe/rte/fdl/security/bean/EgovLoginFailHandler."<init>":(Lorg/egovframe/rte/fdl/security/config/EgovSecurityConfig;)V
       8: areturn
    LineNumberTable:
      line 328: 0
    LocalVariableTable:
      Start  Length  Slot  Name   Signature
          0       9     0  this   Lorg/egovframe/rte/fdl/security/config/EgovSecurityConfiguration;
          0       9     1 securityConfig   Lorg/egovframe/rte/fdl/security/config/EgovSecurityConfig;

  public org.egovframe.rte.fdl.security.bean.RequestMatcherTypeFactoryBean requestMatcherTypeFactoryBean(org.egovframe.rte.fdl.security.config.EgovSecurityConfig);
    Code:
       0: new           #376                // class org/egovframe/rte/fdl/security/bean/RequestMatcherTypeFactoryBean
       3: dup
       4: aload_1
       5: invokespecial #378                // Method org/egovframe/rte/fdl/security/bean/RequestMatcherTypeFactoryBean."<init>":(Lorg/egovframe/rte/fdl/security/config/EgovSecurityConfig;)V
       8: areturn
    LineNumberTable:
      line 333: 0
    LocalVariableTable:
      Start  Length  Slot  Name   Signature
          0       9     0  this   Lorg/egovframe/rte/fdl/security/config/EgovSecurityConfiguration;
          0       9     1 securityConfig   Lorg/egovframe/rte/fdl/security/config/EgovSecurityConfig;

  public org.egovframe.rte.fdl.security.bean.EgovAccessDeniedHandler egovAccessDeniedHandler(org.egovframe.rte.fdl.security.config.EgovSecurityConfig);
    Code:
       0: new           #379                // class org/egovframe/rte/fdl/security/bean/EgovAccessDeniedHandler
       3: dup
       4: aload_1
       5: invokespecial #381                // Method org/egovframe/rte/fdl/security/bean/EgovAccessDeniedHandler."<init>":(Lorg/egovframe/rte/fdl/security/config/EgovSecurityConfig;)V
       8: areturn
    LineNumberTable:
      line 338: 0
    LocalVariableTable:
      Start  Length  Slot  Name   Signature
          0       9     0  this   Lorg/egovframe/rte/fdl/security/config/EgovSecurityConfiguration;
          0       9     1 securityConfig   Lorg/egovframe/rte/fdl/security/config/EgovSecurityConfig;

  public org.springframework.security.web.authentication.LoginUrlAuthenticationEntryPoint loginUrlAuthenticationEntryPoint(org.egovframe.rte.fdl.security.config.EgovSecurityConfig);
    Code:
       0: new           #382                // class org/springframework/security/web/authentication/LoginUrlAuthenticationEntryPoint
       3: dup
       4: aload_1
       5: invokevirtual #384                // Method org/egovframe/rte/fdl/security/config/EgovSecurityConfig.getLoginUrl:()Ljava/lang/String;
       8: invokespecial #387                // Method org/springframework/security/web/authentication/LoginUrlAuthenticationEntryPoint."<init>":(Ljava/lang/String;)V
      11: areturn
    LineNumberTable:
      line 343: 0
    LocalVariableTable:
      Start  Length  Slot  Name   Signature
          0      12     0  this   Lorg/egovframe/rte/fdl/security/config/EgovSecurityConfiguration;
          0      12     1 securityConfig   Lorg/egovframe/rte/fdl/security/config/EgovSecurityConfig;

  public org.egovframe.rte.fdl.security.bean.EgovReloadableFilterInvocationSecurityMetadataSource databaseSecurityMetadataSource(org.egovframe.rte.fdl.security.config.EgovSecurityConfig);
    Code:
       0: new           #82                 // class java/util/LinkedHashMap
       3: dup
       4: aload_0
       5: aload_1
       6: invokevirtual #388                // Method requestMap:(Lorg/egovframe/rte/fdl/security/config/EgovSecurityConfig;)Lorg/egovframe/rte/fdl/security/bean/UrlResourcesMapFactoryBean;
       9: invokevirtual #353                // Method org/egovframe/rte/fdl/security/bean/UrlResourcesMapFactoryBean.getObject:()Ljava/util/LinkedHashMap;
      12: invokespecial #392                // Method java/util/LinkedHashMap."<init>":(Ljava/util/Map;)V
      15: astore_2
      16: new           #82                 // class java/util/LinkedHashMap
      19: dup
      20: invokespecial #84                 // Method java/util/LinkedHashMap."<init>":()V
      23: astore_3
      24: aload_2
      25: invokevirtual #394                // Method java/util/LinkedHashMap.keySet:()Ljava/util/Set;
      28: invokeinterface #398,  1          // InterfaceMethod java/util/Set.iterator:()Ljava/util/Iterator;
      33: astore        4
      35: aload         4
      37: invokeinterface #112,  1          // InterfaceMethod java/util/Iterator.hasNext:()Z
      42: ifeq          76
      45: aload         4
      47: invokeinterface #117,  1          // InterfaceMethod java/util/Iterator.next:()Ljava/lang/Object;
      52: checkcast     #401                // class org/springframework/security/web/util/matcher/RequestMatcher
      55: astore        5
      57: aload_3
      58: aload         5
      60: aload_2
      61: aload         5
      63: invokevirtual #403                // Method java/util/LinkedHashMap.get:(Ljava/lang/Object;)Ljava/lang/Object;
      66: checkcast     #127                // class java/util/Collection
      69: invokevirtual #404                // Method java/util/LinkedHashMap.put:(Ljava/lang/Object;Ljava/lang/Object;)Ljava/lang/Object;
      72: pop
      73: goto          35
      76: new           #405                // class org/egovframe/rte/fdl/security/bean/EgovReloadableFilterInvocationSecurityMetadataSource
      79: dup
      80: aload_3
      81: invokespecial #407                // Method org/egovframe/rte/fdl/security/bean/EgovReloadableFilterInvocationSecurityMetadataSource."<init>":(Ljava/util/LinkedHashMap;)V
      84: astore        4
      86: aload         4
      88: aload_0
      89: aload_1
      90: invokevirtual #325                // Method securedObjectService:(Lorg/egovframe/rte/fdl/security/config/EgovSecurityConfig;)Lorg/egovframe/rte/fdl/security/secureobject/impl/SecuredObjectServiceImpl;
      93: invokevirtual #410                // Method org/egovframe/rte/fdl/security/bean/EgovReloadableFilterInvocationSecurityMetadataSource.setSecuredObjectService:(Lorg/egovframe/rte/fdl/security/secureobject/EgovSecuredObjectService;)V
      96: aload         4
      98: areturn
    LineNumberTable:
      line 348: 0
      line 349: 16
      line 350: 24
      line 351: 57
      line 352: 73
      line 353: 76
      line 354: 86
      line 355: 96
    LocalVariableTable:
      Start  Length  Slot  Name   Signature
         57      16     5   key   Lorg/springframework/security/web/util/matcher/RequestMatcher;
          0      99     0  this   Lorg/egovframe/rte/fdl/security/config/EgovSecurityConfiguration;
          0      99     1 securityConfig   Lorg/egovframe/rte/fdl/security/config/EgovSecurityConfig;
         16      83     2  list   Ljava/util/LinkedHashMap;
         24      75     3 collect   Ljava/util/LinkedHashMap;
         86      13     4 source   Lorg/egovframe/rte/fdl/security/bean/EgovReloadableFilterInvocationSecurityMetadataSource;

  public org.springframework.security.access.AccessDecisionManager accessDecisionManager();
    Code:
       0: new           #411                // class org/springframework/security/access/vote/AffirmativeBased
       3: dup
       4: new           #413                // class org/springframework/security/access/vote/RoleVoter
       7: dup
       8: invokespecial #415                // Method org/springframework/security/access/vote/RoleVoter."<init>":()V
      11: new           #416                // class org/springframework/security/access/vote/AuthenticatedVoter
      14: dup
      15: invokespecial #418                // Method org/springframework/security/access/vote/AuthenticatedVoter."<init>":()V
      18: invokestatic  #419                // InterfaceMethod java/util/List.of:(Ljava/lang/Object;Ljava/lang/Object;)Ljava/util/List;
      21: invokespecial #423                // Method org/springframework/security/access/vote/AffirmativeBased."<init>":(Ljava/util/List;)V
      24: areturn
    LineNumberTable:
      line 364: 0
    LocalVariableTable:
      Start  Length  Slot  Name   Signature
          0      25     0  this   Lorg/egovframe/rte/fdl/security/config/EgovSecurityConfiguration;

  public org.springframework.security.web.access.intercept.FilterSecurityInterceptor filterSecurityInterceptor(org.springframework.security.authentication.AuthenticationManager, org.egovframe.rte.fdl.security.config.EgovSecurityConfig);
    Code:
       0: new           #426                // class org/springframework/security/web/access/intercept/FilterSecurityInterceptor
       3: dup
       4: invokespecial #428                // Method org/springframework/security/web/access/intercept/FilterSecurityInterceptor."<init>":()V
       7: astore_3
       8: aload_3
       9: aload_1
      10: invokevirtual #429                // Method org/springframework/security/web/access/intercept/FilterSecurityInterceptor.setAuthenticationManager:(Lorg/springframework/security/authentication/AuthenticationManager;)V
      13: aload_3
      14: aload_0
      15: invokevirtual #430                // Method accessDecisionManager:()Lorg/springframework/security/access/AccessDecisionManager;
      18: invokevirtual #434                // Method org/springframework/security/web/access/intercept/FilterSecurityInterceptor.setAccessDecisionManager:(Lorg/springframework/security/access/AccessDecisionManager;)V
      21: aload_3
      22: aload_0
      23: aload_2
      24: invokevirtual #438                // Method databaseSecurityMetadataSource:(Lorg/egovframe/rte/fdl/security/config/EgovSecurityConfig;)Lorg/egovframe/rte/fdl/security/bean/EgovReloadableFilterInvocationSecurityMetadataSource;
      27: invokevirtual #442                // Method org/springframework/security/web/access/intercept/FilterSecurityInterceptor.setSecurityMetadataSource:(Lorg/springframework/security/web/access/intercept/FilterInvocationSecurityMetadataSource;)V
      30: aload_3
      31: areturn
    LineNumberTable:
      line 369: 0
      line 370: 8
      line 371: 13
      line 372: 21
      line 373: 30
    LocalVariableTable:
      Start  Length  Slot  Name   Signature
          0      32     0  this   Lorg/egovframe/rte/fdl/security/config/EgovSecurityConfiguration;
          0      32     1 authManager   Lorg/springframework/security/authentication/AuthenticationManager;
          0      32     2 securityConfig   Lorg/egovframe/rte/fdl/security/config/EgovSecurityConfig;
          8      24     3 interceptor   Lorg/springframework/security/web/access/intercept/FilterSecurityInterceptor;

  public org.springframework.security.web.context.SecurityContextRepository securityContextRepository();
    Code:
       0: new           #446                // class org/springframework/security/web/context/HttpSessionSecurityContextRepository
       3: dup
       4: invokespecial #448                // Method org/springframework/security/web/context/HttpSessionSecurityContextRepository."<init>":()V
       7: areturn
    LineNumberTable:
      line 378: 0
    LocalVariableTable:
      Start  Length  Slot  Name   Signature
          0       8     0  this   Lorg/egovframe/rte/fdl/security/config/EgovSecurityConfiguration;

  public org.springframework.security.web.SecurityFilterChain securityFilterChain(org.springframework.security.config.annotation.web.builders.HttpSecurity, org.springframework.security.authentication.AuthenticationManager, org.springframework.security.web.context.SecurityContextRepository, org.springframework.security.web.access.intercept.FilterSecurityInterceptor, org.egovframe.rte.fdl.security.config.EgovSecurityConfig) throws java.lang.Exception;
    Code:
       0: aload_1
       1: invokestatic  #449                // InterfaceMethod org/springframework/security/config/Customizer.withDefaults:()Lorg/springframework/security/config/Customizer;
       4: invokevirtual #455                // Method org/springframework/security/config/annotation/web/builders/HttpSecurity.anonymous:(Lorg/springframework/security/config/Customizer;)Lorg/springframework/security/config/annotation/web/builders/HttpSecurity;
       7: pop
       8: invokestatic  #461                // Method org/springframework/security/web/servlet/util/matcher/PathPatternRequestMatcher.withDefaults:()Lorg/springframework/security/web/servlet/util/matcher/PathPatternRequestMatcher$Builder;
      11: astore        6
      13: aload         5
      15: invokevirtual #466                // Method org/egovframe/rte/fdl/security/config/EgovSecurityConfig.getPermitAllList:()Ljava/lang/String;
      18: aload         6
      20: invokestatic  #469                // Method buildPermitAllMatchers:(Ljava/lang/String;Lorg/springframework/security/web/servlet/util/matcher/PathPatternRequestMatcher$Builder;)Ljava/util/List;
      23: astore        7
      25: aload_1
      26: aload         7
      28: invokedynamic #473,  0            // InvokeDynamic #2:customize:(Ljava/util/List;)Lorg/springframework/security/config/Customizer;
      33: invokevirtual #477                // Method org/springframework/security/config/annotation/web/builders/HttpSecurity.authorizeHttpRequests:(Lorg/springframework/security/config/Customizer;)Lorg/springframework/security/config/annotation/web/builders/HttpSecurity;
      36: pop
      37: aload_1
      38: aload         4
      40: ldc_w         #480                // class org/springframework/security/web/access/intercept/AuthorizationFilter
      43: invokevirtual #482                // Method org/springframework/security/config/annotation/web/builders/HttpSecurity.addFilterBefore:(Ljakarta/servlet/Filter;Ljava/lang/Class;)Lorg/springframework/security/config/annotation/web/builders/HttpSecurity;
      46: pop
      47: aload_1
      48: aload_3
      49: invokedynamic #486,  0            // InvokeDynamic #3:customize:(Lorg/springframework/security/web/context/SecurityContextRepository;)Lorg/springframework/security/config/Customizer;
      54: invokevirtual #489                // Method org/springframework/security/config/annotation/web/builders/HttpSecurity.securityContext:(Lorg/springframework/security/config/Customizer;)Lorg/springframework/security/config/annotation/web/builders/HttpSecurity;
      57: pop
      58: aload_1
      59: aload_2
      60: invokevirtual #492                // Method org/springframework/security/config/annotation/web/builders/HttpSecurity.authenticationManager:(Lorg/springframework/security/authentication/AuthenticationManager;)Lorg/springframework/security/config/annotation/web/builders/HttpSecurity;
      63: pop
      64: aload_1
      65: aload         5
      67: invokedynamic #495,  0            // InvokeDynamic #4:customize:(Lorg/egovframe/rte/fdl/security/config/EgovSecurityConfig;)Lorg/springframework/security/config/Customizer;
      72: invokevirtual #498                // Method org/springframework/security/config/annotation/web/builders/HttpSecurity.formLogin:(Lorg/springframework/security/config/Customizer;)Lorg/springframework/security/config/annotation/web/builders/HttpSecurity;
      75: pop
      76: aload_1
      77: aload         5
      79: invokedynamic #501,  0            // InvokeDynamic #5:customize:(Lorg/egovframe/rte/fdl/security/config/EgovSecurityConfig;)Lorg/springframework/security/config/Customizer;
      84: invokevirtual #502                // Method org/springframework/security/config/annotation/web/builders/HttpSecurity.logout:(Lorg/springframework/security/config/Customizer;)Lorg/springframework/security/config/annotation/web/builders/HttpSecurity;
      87: pop
      88: aload         5
      90: invokevirtual #505                // Method org/egovframe/rte/fdl/security/config/EgovSecurityConfig.isCsrf:()Z
      93: ifne          109
      96: aload_1
      97: invokedynamic #508,  0            // InvokeDynamic #6:customize:()Lorg/springframework/security/config/Customizer;
     102: invokevirtual #510                // Method org/springframework/security/config/annotation/web/builders/HttpSecurity.csrf:(Lorg/springframework/security/config/Customizer;)Lorg/springframework/security/config/annotation/web/builders/HttpSecurity;
     105: pop
     106: goto          117
     109: aload_1
     110: invokestatic  #449                // InterfaceMethod org/springframework/security/config/Customizer.withDefaults:()Lorg/springframework/security/config/Customizer;
     113: invokevirtual #510                // Method org/springframework/security/config/annotation/web/builders/HttpSecurity.csrf:(Lorg/springframework/security/config/Customizer;)Lorg/springframework/security/config/annotation/web/builders/HttpSecurity;
     116: pop
     117: aload         5
     119: invokevirtual #513                // Method org/egovframe/rte/fdl/security/config/EgovSecurityConfig.getConcurrentMaxSessons:()I
     122: iconst_1
     123: invokestatic  #516                // Method java/lang/Math.max:(II)I
     126: istore        8
     128: aload_1
     129: iload         8
     131: aload         5
     133: invokedynamic #522,  0            // InvokeDynamic #7:customize:(ILorg/egovframe/rte/fdl/security/config/EgovSecurityConfig;)Lorg/springframework/security/config/Customizer;
     138: invokevirtual #525                // Method org/springframework/security/config/annotation/web/builders/HttpSecurity.sessionManagement:(Lorg/springframework/security/config/Customizer;)Lorg/springframework/security/config/annotation/web/builders/HttpSecurity;
     141: pop
     142: aload_1
     143: aload_0
     144: aload         5
     146: invokedynamic #528,  0            // InvokeDynamic #8:customize:(Lorg/egovframe/rte/fdl/security/config/EgovSecurityConfiguration;Lorg/egovframe/rte/fdl/security/config/EgovSecurityConfig;)Lorg/springframework/security/config/Customizer;
     151: invokevirtual #531                // Method org/springframework/security/config/annotation/web/builders/HttpSecurity.exceptionHandling:(Lorg/springframework/security/config/Customizer;)Lorg/springframework/security/config/annotation/web/builders/HttpSecurity;
     154: pop
     155: aload_1
     156: aload         5
     158: invokedynamic #534,  0            // InvokeDynamic #9:customize:(Lorg/egovframe/rte/fdl/security/config/EgovSecurityConfig;)Lorg/springframework/security/config/Customizer;
     163: invokevirtual #535                // Method org/springframework/security/config/annotation/web/builders/HttpSecurity.headers:(Lorg/springframework/security/config/Customizer;)Lorg/springframework/security/config/annotation/web/builders/HttpSecurity;
     166: pop
     167: aload_1
     168: aload_0
     169: aload         5
     171: invokevirtual #538                // Method usernamePasswordAuthenticationFilter:(Lorg/egovframe/rte/fdl/security/config/EgovSecurityConfig;)Lorg/springframework/security/web/authentication/UsernamePasswordAuthenticationFilter;
     174: ldc_w         #362                // class org/springframework/security/web/authentication/UsernamePasswordAuthenticationFilter
     177: invokevirtual #482                // Method org/springframework/security/config/annotation/web/builders/HttpSecurity.addFilterBefore:(Ljakarta/servlet/Filter;Ljava/lang/Class;)Lorg/springframework/security/config/annotation/web/builders/HttpSecurity;
     180: pop
     181: aload_1
     182: invokevirtual #542                // Method org/springframework/security/config/annotation/web/builders/HttpSecurity.build:()Ljava/lang/Object;
     185: checkcast     #545                // class org/springframework/security/web/SecurityFilterChain
     188: areturn
    LineNumberTable:
      line 392: 0
      line 395: 8
      line 398: 13
      line 401: 25
      line 410: 37
      line 412: 47
      line 415: 58
      line 417: 64
      line 425: 76
      line 431: 88
      line 432: 96
      line 434: 109
      line 438: 117
      line 439: 128
      line 450: 142
      line 455: 155
      line 490: 167
      line 492: 181
    LocalVariableTable:
      Start  Length  Slot  Name   Signature
          0     189     0  this   Lorg/egovframe/rte/fdl/security/config/EgovSecurityConfiguration;
          0     189     1  http   Lorg/springframework/security/config/annotation/web/builders/HttpSecurity;
          0     189     2 authManager   Lorg/springframework/security/authentication/AuthenticationManager;
          0     189     3 securityContextRepository   Lorg/springframework/security/web/context/SecurityContextRepository;
          0     189     4 filterSecurityInterceptor   Lorg/springframework/security/web/access/intercept/FilterSecurityInterceptor;
          0     189     5 securityConfig   Lorg/egovframe/rte/fdl/security/config/EgovSecurityConfig;
         13     176     6    pp   Lorg/springframework/security/web/servlet/util/matcher/PathPatternRequestMatcher$Builder;
         25     164     7 permitAll   Ljava/util/List;
        128      61     8 maxSessions   I

  private static void lambda$securityFilterChain$10(org.egovframe.rte.fdl.security.config.EgovSecurityConfig, org.springframework.security.config.annotation.web.configurers.HeadersConfigurer);
    Code:
       0: aload_0
       1: invokevirtual #547                // Method org/egovframe/rte/fdl/security/config/EgovSecurityConfig.isSniff:()Z
       4: ifeq          18
       7: aload_1
       8: invokestatic  #449                // InterfaceMethod org/springframework/security/config/Customizer.withDefaults:()Lorg/springframework/security/config/Customizer;
      11: invokevirtual #550                // Method org/springframework/security/config/annotation/web/configurers/HeadersConfigurer.contentTypeOptions:(Lorg/springframework/security/config/Customizer;)Lorg/springframework/security/config/annotation/web/configurers/HeadersConfigurer;
      14: pop
      15: goto          28
      18: aload_1
      19: invokedynamic #556,  0            // InvokeDynamic #10:customize:()Lorg/springframework/security/config/Customizer;
      24: invokevirtual #550                // Method org/springframework/security/config/annotation/web/configurers/HeadersConfigurer.contentTypeOptions:(Lorg/springframework/security/config/Customizer;)Lorg/springframework/security/config/annotation/web/configurers/HeadersConfigurer;
      27: pop
      28: aload_0
      29: invokevirtual #557                // Method org/egovframe/rte/fdl/security/config/EgovSecurityConfig.getXframeOptions:()Ljava/lang/String;
      32: astore_2
      33: aload_2
      34: invokestatic  #26                 // Method org/springframework/util/ObjectUtils.isEmpty:(Ljava/lang/Object;)Z
      37: ifne          176
      40: aload_2
      41: invokevirtual #43                 // Method java/lang/String.trim:()Ljava/lang/String;
      44: getstatic     #560                // Field java/util/Locale.ROOT:Ljava/util/Locale;
      47: invokevirtual #566                // Method java/lang/String.toUpperCase:(Ljava/util/Locale;)Ljava/lang/String;
      50: astore_3
      51: iconst_m1
      52: istore        4
      54: aload_3
      55: invokevirtual #154                // Method java/lang/String.hashCode:()I
      58: lookupswitch  { // 2

           -1905676600: 100

            -445843700: 84
               default: 113
          }
      84: aload_3
      85: ldc_w         #569                // String SAMEORIGIN
      88: invokevirtual #159                // Method java/lang/String.equals:(Ljava/lang/Object;)Z
      91: ifeq          113
      94: iconst_0
      95: istore        4
      97: goto          113
     100: aload_3
     101: ldc_w         #571                // String DISABLE
     104: invokevirtual #159                // Method java/lang/String.equals:(Ljava/lang/Object;)Z
     107: ifeq          113
     110: iconst_1
     111: istore        4
     113: iload         4
     115: lookupswitch  { // 2

                     0: 140

                     1: 153
               default: 166
          }
     140: aload_1
     141: invokedynamic #573,  0            // InvokeDynamic #11:customize:()Lorg/springframework/security/config/Customizer;
     146: invokevirtual #574                // Method org/springframework/security/config/annotation/web/configurers/HeadersConfigurer.frameOptions:(Lorg/springframework/security/config/Customizer;)Lorg/springframework/security/config/annotation/web/configurers/HeadersConfigurer;
     149: pop
     150: goto          176
     153: aload_1
     154: invokedynamic #577,  0            // InvokeDynamic #12:customize:()Lorg/springframework/security/config/Customizer;
     159: invokevirtual #574                // Method org/springframework/security/config/annotation/web/configurers/HeadersConfigurer.frameOptions:(Lorg/springframework/security/config/Customizer;)Lorg/springframework/security/config/annotation/web/configurers/HeadersConfigurer;
     162: pop
     163: goto          176
     166: aload_1
     167: invokedynamic #578,  0            // InvokeDynamic #13:customize:()Lorg/springframework/security/config/Customizer;
     172: invokevirtual #574                // Method org/springframework/security/config/annotation/web/configurers/HeadersConfigurer.frameOptions:(Lorg/springframework/security/config/Customizer;)Lorg/springframework/security/config/annotation/web/configurers/HeadersConfigurer;
     175: pop
     176: aload_0
     177: invokevirtual #579                // Method org/egovframe/rte/fdl/security/config/EgovSecurityConfig.isXssProtection:()Z
     180: ifeq          194
     183: aload_1
     184: invokestatic  #449                // InterfaceMethod org/springframework/security/config/Customizer.withDefaults:()Lorg/springframework/security/config/Customizer;
     187: invokevirtual #582                // Method org/springframework/security/config/annotation/web/configurers/HeadersConfigurer.xssProtection:(Lorg/springframework/security/config/Customizer;)Lorg/springframework/security/config/annotation/web/configurers/HeadersConfigurer;
     190: pop
     191: goto          204
     194: aload_1
     195: invokedynamic #585,  0            // InvokeDynamic #14:customize:()Lorg/springframework/security/config/Customizer;
     200: invokevirtual #582                // Method org/springframework/security/config/annotation/web/configurers/HeadersConfigurer.xssProtection:(Lorg/springframework/security/config/Customizer;)Lorg/springframework/security/config/annotation/web/configurers/HeadersConfigurer;
     203: pop
     204: aload_0
     205: invokevirtual #586                // Method org/egovframe/rte/fdl/security/config/EgovSecurityConfig.isCacheControl:()Z
     208: ifeq          224
     211: aload_1
     212: invokedynamic #589,  0            // InvokeDynamic #15:customize:()Lorg/springframework/security/config/Customizer;
     217: invokevirtual #590                // Method org/springframework/security/config/annotation/web/configurers/HeadersConfigurer.cacheControl:(Lorg/springframework/security/config/Customizer;)Lorg/springframework/security/config/annotation/web/configurers/HeadersConfigurer;
     220: pop
     221: goto          232
     224: aload_1
     225: invokestatic  #449                // InterfaceMethod org/springframework/security/config/Customizer.withDefaults:()Lorg/springframework/security/config/Customizer;
     228: invokevirtual #590                // Method org/springframework/security/config/annotation/web/configurers/HeadersConfigurer.cacheControl:(Lorg/springframework/security/config/Customizer;)Lorg/springframework/security/config/annotation/web/configurers/HeadersConfigurer;
     231: pop
     232: return
    LineNumberTable:
      line 458: 0
      line 459: 7
      line 461: 18
      line 465: 28
      line 466: 33
      line 467: 40
      line 468: 140
      line 469: 153
      line 470: 166
      line 475: 176
      line 476: 183
      line 478: 194
      line 482: 204
      line 483: 211
      line 485: 224
      line 488: 232
    LocalVariableTable:
      Start  Length  Slot  Name   Signature
          0     233     0 securityConfig   Lorg/egovframe/rte/fdl/security/config/EgovSecurityConfig;
          0     233     1 headers   Lorg/springframework/security/config/annotation/web/configurers/HeadersConfigurer;
         33     200     2   xfo   Ljava/lang/String;

  private void lambda$securityFilterChain$9(org.egovframe.rte.fdl.security.config.EgovSecurityConfig, org.springframework.security.config.annotation.web.configurers.ExceptionHandlingConfigurer);
    Code:
       0: aload_2
       1: aload_0
       2: aload_1
       3: invokevirtual #593                // Method loginUrlAuthenticationEntryPoint:(Lorg/egovframe/rte/fdl/security/config/EgovSecurityConfig;)Lorg/springframework/security/web/authentication/LoginUrlAuthenticationEntryPoint;
       6: invokevirtual #597                // Method org/springframework/security/config/annotation/web/configurers/ExceptionHandlingConfigurer.authenticationEntryPoint:(Lorg/springframework/security/web/AuthenticationEntryPoint;)Lorg/springframework/security/config/annotation/web/configurers/ExceptionHandlingConfigurer;
       9: aload_0
      10: aload_1
      11: invokevirtual #603                // Method egovAccessDeniedHandler:(Lorg/egovframe/rte/fdl/security/config/EgovSecurityConfig;)Lorg/egovframe/rte/fdl/security/bean/EgovAccessDeniedHandler;
      14: invokevirtual #607                // Method org/springframework/security/config/annotation/web/configurers/ExceptionHandlingConfigurer.accessDeniedHandler:(Lorg/springframework/security/web/access/AccessDeniedHandler;)Lorg/springframework/security/config/annotation/web/configurers/ExceptionHandlingConfigurer;
      17: pop
      18: return
    LineNumberTable:
      line 451: 0
      line 452: 11
      line 451: 18
    LocalVariableTable:
      Start  Length  Slot  Name   Signature
          0      19     0  this   Lorg/egovframe/rte/fdl/security/config/EgovSecurityConfiguration;
          0      19     1 securityConfig   Lorg/egovframe/rte/fdl/security/config/EgovSecurityConfig;
          0      19     2 exceptionHandling   Lorg/springframework/security/config/annotation/web/configurers/ExceptionHandlingConfigurer;

  private static void lambda$securityFilterChain$8(int, org.egovframe.rte.fdl.security.config.EgovSecurityConfig, org.springframework.security.config.annotation.web.configurers.SessionManagementConfigurer);
    Code:
       0: aload_2
       1: iload_0
       2: aload_1
       3: invokedynamic #611,  0            // InvokeDynamic #16:customize:(ILorg/egovframe/rte/fdl/security/config/EgovSecurityConfig;)Lorg/springframework/security/config/Customizer;
       8: invokevirtual #612                // Method org/springframework/security/config/annotation/web/configurers/SessionManagementConfigurer.sessionConcurrency:(Lorg/springframework/security/config/Customizer;)Lorg/springframework/security/config/annotation/web/configurers/SessionManagementConfigurer;
      11: pop
      12: return
    LineNumberTable:
      line 439: 0
      line 440: 8
      line 439: 12
    LocalVariableTable:
      Start  Length  Slot  Name   Signature
          0      13     0 maxSessions   I
          0      13     1 securityConfig   Lorg/egovframe/rte/fdl/security/config/EgovSecurityConfig;
          0      13     2 session   Lorg/springframework/security/config/annotation/web/configurers/SessionManagementConfigurer;

  private static void lambda$securityFilterChain$7(int, org.egovframe.rte.fdl.security.config.EgovSecurityConfig, org.springframework.security.config.annotation.web.configurers.SessionManagementConfigurer$ConcurrencyControlConfigurer);
    Code:
       0: aload_2
       1: iload_0
       2: invokevirtual #618                // Method org/springframework/security/config/annotation/web/configurers/SessionManagementConfigurer$ConcurrencyControlConfigurer.maximumSessions:(I)Lorg/springframework/security/config/annotation/web/configurers/SessionManagementConfigurer$ConcurrencyControlConfigurer;
       5: pop
       6: aload_1
       7: invokevirtual #624                // Method org/egovframe/rte/fdl/security/config/EgovSecurityConfig.getConcurrentExpiredUrl:()Ljava/lang/String;
      10: invokestatic  #26                 // Method org/springframework/util/ObjectUtils.isEmpty:(Ljava/lang/Object;)Z
      13: ifne          25
      16: aload_2
      17: aload_1
      18: invokevirtual #624                // Method org/egovframe/rte/fdl/security/config/EgovSecurityConfig.getConcurrentExpiredUrl:()Ljava/lang/String;
      21: invokevirtual #627                // Method org/springframework/security/config/annotation/web/configurers/SessionManagementConfigurer$ConcurrencyControlConfigurer.expiredUrl:(Ljava/lang/String;)Lorg/springframework/security/config/annotation/web/configurers/SessionManagementConfigurer$ConcurrencyControlConfigurer;
      24: pop
      25: aload_2
      26: aload_1
      27: invokevirtual #631                // Method org/egovframe/rte/fdl/security/config/EgovSecurityConfig.isErrorIfMaximumExceeded:()Z
      30: invokevirtual #634                // Method org/springframework/security/config/annotation/web/configurers/SessionManagementConfigurer$ConcurrencyControlConfigurer.maxSessionsPreventsLogin:(Z)Lorg/springframework/security/config/annotation/web/configurers/SessionManagementConfigurer$ConcurrencyControlConfigurer;
      33: pop
      34: return
    LineNumberTable:
      line 441: 0
      line 442: 6
      line 443: 16
      line 445: 25
      line 446: 34
    LocalVariableTable:
      Start  Length  Slot  Name   Signature
          0      35     0 maxSessions   I
          0      35     1 securityConfig   Lorg/egovframe/rte/fdl/security/config/EgovSecurityConfig;
          0      35     2 concurrency   Lorg/springframework/security/config/annotation/web/configurers/SessionManagementConfigurer$ConcurrencyControlConfigurer;

  private static void lambda$securityFilterChain$6(org.egovframe.rte.fdl.security.config.EgovSecurityConfig, org.springframework.security.config.annotation.web.configurers.LogoutConfigurer);
    Code:
       0: aload_1
       1: aload_0
       2: invokevirtual #638                // Method org/egovframe/rte/fdl/security/config/EgovSecurityConfig.getLogoutUrl:()Ljava/lang/String;
       5: invokevirtual #641                // Method org/springframework/security/config/annotation/web/configurers/LogoutConfigurer.logoutUrl:(Ljava/lang/String;)Lorg/springframework/security/config/annotation/web/configurers/LogoutConfigurer;
       8: aload_0
       9: invokevirtual #647                // Method org/egovframe/rte/fdl/security/config/EgovSecurityConfig.getLogoutSuccessUrl:()Ljava/lang/String;
      12: invokevirtual #650                // Method org/springframework/security/config/annotation/web/configurers/LogoutConfigurer.logoutSuccessUrl:(Ljava/lang/String;)Lorg/springframework/security/config/annotation/web/configurers/LogoutConfigurer;
      15: invokevirtual #653                // Method org/springframework/security/config/annotation/web/configurers/LogoutConfigurer.permitAll:()Lorg/springframework/security/config/annotation/web/configurers/LogoutConfigurer;
      18: pop
      19: return
    LineNumberTable:
      line 425: 0
      line 426: 2
      line 427: 9
      line 428: 15
      line 425: 19
    LocalVariableTable:
      Start  Length  Slot  Name   Signature
          0      20     0 securityConfig   Lorg/egovframe/rte/fdl/security/config/EgovSecurityConfig;
          0      20     1 logout   Lorg/springframework/security/config/annotation/web/configurers/LogoutConfigurer;

  private static void lambda$securityFilterChain$5(org.egovframe.rte.fdl.security.config.EgovSecurityConfig, org.springframework.security.config.annotation.web.configurers.FormLoginConfigurer);
    Code:
       0: aload_1
       1: aload_0
       2: invokevirtual #384                // Method org/egovframe/rte/fdl/security/config/EgovSecurityConfig.getLoginUrl:()Ljava/lang/String;
       5: invokevirtual #657                // Method org/springframework/security/config/annotation/web/configurers/FormLoginConfigurer.loginPage:(Ljava/lang/String;)Lorg/springframework/security/config/annotation/web/configurers/FormLoginConfigurer;
       8: aload_0
       9: invokevirtual #663                // Method org/egovframe/rte/fdl/security/config/EgovSecurityConfig.getLoginProcessUrl:()Ljava/lang/String;
      12: invokevirtual #666                // Method org/springframework/security/config/annotation/web/configurers/FormLoginConfigurer.loginProcessingUrl:(Ljava/lang/String;)Lorg/springframework/security/config/annotation/web/configurers/AbstractAuthenticationFilterConfigurer;
      15: checkcast     #658                // class org/springframework/security/config/annotation/web/configurers/FormLoginConfigurer
      18: aload_0
      19: invokevirtual #670                // Method org/egovframe/rte/fdl/security/config/EgovSecurityConfig.getDefaultTargetUrl:()Ljava/lang/String;
      22: aload_0
      23: invokevirtual #673                // Method org/egovframe/rte/fdl/security/config/EgovSecurityConfig.isAlwaysUseDefaultTargetUrl:()Z
      26: invokevirtual #676                // Method org/springframework/security/config/annotation/web/configurers/FormLoginConfigurer.defaultSuccessUrl:(Ljava/lang/String;Z)Lorg/springframework/security/config/annotation/web/configurers/AbstractAuthenticationFilterConfigurer;
      29: checkcast     #658                // class org/springframework/security/config/annotation/web/configurers/FormLoginConfigurer
      32: aload_0
      33: invokevirtual #680                // Method org/egovframe/rte/fdl/security/config/EgovSecurityConfig.getLoginFailureUrl:()Ljava/lang/String;
      36: invokevirtual #683                // Method org/springframework/security/config/annotation/web/configurers/FormLoginConfigurer.failureUrl:(Ljava/lang/String;)Lorg/springframework/security/config/annotation/web/configurers/AbstractAuthenticationFilterConfigurer;
      39: checkcast     #658                // class org/springframework/security/config/annotation/web/configurers/FormLoginConfigurer
      42: invokevirtual #686                // Method org/springframework/security/config/annotation/web/configurers/FormLoginConfigurer.permitAll:()Lorg/springframework/security/config/annotation/web/configurers/AbstractAuthenticationFilterConfigurer;
      45: pop
      46: return
    LineNumberTable:
      line 421: 0
      line 418: 2
      line 419: 9
      line 420: 19
      line 421: 33
      line 422: 42
      line 421: 46
    LocalVariableTable:
      Start  Length  Slot  Name   Signature
          0      47     0 securityConfig   Lorg/egovframe/rte/fdl/security/config/EgovSecurityConfig;
          0      47     1  form   Lorg/springframework/security/config/annotation/web/configurers/FormLoginConfigurer;

  private static void lambda$securityFilterChain$4(org.springframework.security.web.context.SecurityContextRepository, org.springframework.security.config.annotation.web.configurers.SecurityContextConfigurer);
    Code:
       0: aload_1
       1: aload_0
       2: invokevirtual #689                // Method org/springframework/security/config/annotation/web/configurers/SecurityContextConfigurer.securityContextRepository:(Lorg/springframework/security/web/context/SecurityContextRepository;)Lorg/springframework/security/config/annotation/web/configurers/SecurityContextConfigurer;
       5: pop
       6: return
    LineNumberTable:
      line 412: 0
    LocalVariableTable:
      Start  Length  Slot  Name   Signature
          0       7     0 securityContextRepository   Lorg/springframework/security/web/context/SecurityContextRepository;
          0       7     1    sc   Lorg/springframework/security/config/annotation/web/configurers/SecurityContextConfigurer;

  private static void lambda$securityFilterChain$3(java.util.List, org.springframework.security.config.annotation.web.configurers.AuthorizeHttpRequestsConfigurer$AuthorizationManagerRequestMatcherRegistry);
    Code:
       0: aload_0
       1: invokeinterface #695,  1          // InterfaceMethod java/util/List.isEmpty:()Z
       6: ifne          33
       9: aload_1
      10: aload_0
      11: iconst_0
      12: anewarray     #401                // class org/springframework/security/web/util/matcher/RequestMatcher
      15: invokeinterface #696,  2          // InterfaceMethod java/util/List.toArray:([Ljava/lang/Object;)[Ljava/lang/Object;
      20: checkcast     #700                // class "[Lorg/springframework/security/web/util/matcher/RequestMatcher;"
      23: invokevirtual #702                // Method org/springframework/security/config/annotation/web/configurers/AuthorizeHttpRequestsConfigurer$AuthorizationManagerRequestMatcherRegistry.requestMatchers:([Lorg/springframework/security/web/util/matcher/RequestMatcher;)Ljava/lang/Object;
      26: checkcast     #708                // class org/springframework/security/config/annotation/web/configurers/AuthorizeHttpRequestsConfigurer$AuthorizedUrl
      29: invokevirtual #710                // Method org/springframework/security/config/annotation/web/configurers/AuthorizeHttpRequestsConfigurer$AuthorizedUrl.permitAll:()Lorg/springframework/security/config/annotation/web/configurers/AuthorizeHttpRequestsConfigurer$AuthorizationManagerRequestMatcherRegistry;
      32: pop
      33: aload_1
      34: invokevirtual #713                // Method org/springframework/security/config/annotation/web/configurers/AuthorizeHttpRequestsConfigurer$AuthorizationManagerRequestMatcherRegistry.anyRequest:()Ljava/lang/Object;
      37: checkcast     #708                // class org/springframework/security/config/annotation/web/configurers/AuthorizeHttpRequestsConfigurer$AuthorizedUrl
      40: invokevirtual #716                // Method org/springframework/security/config/annotation/web/configurers/AuthorizeHttpRequestsConfigurer$AuthorizedUrl.authenticated:()Lorg/springframework/security/config/annotation/web/configurers/AuthorizeHttpRequestsConfigurer$AuthorizationManagerRequestMatcherRegistry;
      43: pop
      44: return
    LineNumberTable:
      line 402: 0
      line 403: 9
      line 406: 33
      line 407: 44
    LocalVariableTable:
      Start  Length  Slot  Name   Signature
          0      45     0 permitAll   Ljava/util/List;
          0      45     1  auth   Lorg/springframework/security/config/annotation/web/configurers/AuthorizeHttpRequestsConfigurer$AuthorizationManagerRequestMatcherRegistry;

  private static int lambda$loadUrlAuthorizationsFromDb$2(java.lang.String, java.lang.String);
    Code:
       0: aload_0
       1: invokestatic  #719                // Method calculateUrlSpecificity:(Ljava/lang/String;)I
       4: istore_2
       5: aload_1
       6: invokestatic  #719                // Method calculateUrlSpecificity:(Ljava/lang/String;)I
       9: istore_3
      10: iload_3
      11: iload_2
      12: invokestatic  #723                // Method java/lang/Integer.compare:(II)I
      15: ireturn
    LineNumberTable:
      line 160: 0
      line 161: 5
      line 162: 10
    LocalVariableTable:
      Start  Length  Slot  Name   Signature
          0      16     0  url1   Ljava/lang/String;
          0      16     1  url2   Ljava/lang/String;
          5      11     2 specificity1   I
         10       6     3 specificity2   I

  private static void lambda$loadUrlAuthorizationsFromDb$1(java.util.Map, java.util.List, java.sql.ResultSet) throws java.sql.SQLException;
    Code:
       0: aload_2
       1: ldc_w         #727                // String url
       4: invokeinterface #729,  2          // InterfaceMethod java/sql/ResultSet.getString:(Ljava/lang/String;)Ljava/lang/String;
       9: astore_3
      10: aload_2
      11: ldc_w         #735                // String authority
      14: invokeinterface #729,  2          // InterfaceMethod java/sql/ResultSet.getString:(Ljava/lang/String;)Ljava/lang/String;
      19: astore        4
      21: aload_3
      22: invokestatic  #26                 // Method org/springframework/util/ObjectUtils.isEmpty:(Ljava/lang/Object;)Z
      25: ifne          77
      28: aload         4
      30: invokestatic  #26                 // Method org/springframework/util/ObjectUtils.isEmpty:(Ljava/lang/Object;)Z
      33: ifne          77
      36: aload_0
      37: aload_3
      38: invokeinterface #737,  2          // InterfaceMethod java/util/Map.containsKey:(Ljava/lang/Object;)Z
      43: ifne          54
      46: aload_1
      47: aload_3
      48: invokeinterface #71,  2           // InterfaceMethod java/util/List.add:(Ljava/lang/Object;)Z
      53: pop
      54: aload_0
      55: aload_3
      56: invokedynamic #740,  0            // InvokeDynamic #17:apply:()Ljava/util/function/Function;
      61: invokeinterface #744,  3          // InterfaceMethod java/util/Map.computeIfAbsent:(Ljava/lang/Object;Ljava/util/function/Function;)Ljava/lang/Object;
      66: checkcast     #127                // class java/util/Collection
      69: aload         4
      71: invokeinterface #748,  2          // InterfaceMethod java/util/Collection.add:(Ljava/lang/Object;)Z
      76: pop
      77: return
    LineNumberTable:
      line 144: 0
      line 145: 10
      line 146: 21
      line 148: 36
      line 149: 46
      line 151: 54
      line 153: 77
    LocalVariableTable:
      Start  Length  Slot  Name   Signature
          0      78     0 urlToAuthorities   Ljava/util/Map;
          0      78     1 urlOrder   Ljava/util/List;
          0      78     2    rs   Ljava/sql/ResultSet;
         10      68     3   url   Ljava/lang/String;
         21      57     4  auth   Ljava/lang/String;

  private static java.util.Collection lambda$loadUrlAuthorizationsFromDb$0(java.lang.String);
    Code:
       0: new           #32                 // class java/util/ArrayList
       3: dup
       4: invokespecial #34                 // Method java/util/ArrayList."<init>":()V
       7: areturn
    LineNumberTable:
      line 151: 0
    LocalVariableTable:
      Start  Length  Slot  Name   Signature
          0       8     0     k   Ljava/lang/String;
}
